{
  "Title": "C\u00f4 v\u1ee3 cao l\u00e3nh c\u1ee7a t\u1ed5ng t\u00e0i c\u1ea5p cao",
  "URL": "co-vo-cao-lanh-cua-tong-tai-cap-cao",
  "CoverImage": "co-vo-cao-lanh-cua-tong-tai-cap-cao.jpg",
  "CreateAt": "04/01/2024",
  "statusComic": 0,
  "Category": [
    "Comedy",
    "Manhua",
    "Ng\u00f4n T\u00ecnh",
    "Romance",
    "Shoujo",
    "Truy\u1ec7n M\u00e0u"
  ],
  "LastChapter": "chapter-21",
  "TotalChapter": 21,
  "Chapters": {
    "urlChapter": "chapter-21",
    "dateUpdateChapter": "2024-01-04 11:10:45"
  }
}