{
  "Title": "Cu\u1ed9c H\u00f4n Nh\u00e2n N\u00e0y D\u00f9 Sao C\u0169ng S\u1ebd Tan V\u1ee1 M\u00e0 Th\u00f4i",
  "URL": "cuoc-hon-nhan-nay-du-sao-cung-se-tan-vo-ma-thoi",
  "CoverImage": "cuoc-hon-nhan-nay-du-sao-cung-se-tan-vo-ma-thoi.jpg",
  "CreateAt": "21/12/2023",
  "statusComic": 0,
  "Category": [
    "Chuy\u1ec3n Sinh",
    "Manhwa",
    "Ng\u00f4n T\u00ecnh",
    "Romance",
    "Truy\u1ec7n M\u00e0u"
  ],
  "LastChapter": "chapter-69",
  "TotalChapter": 69,
  "Chapters": [
    {
      "urlChapter": "chapter-69",
      "dateUpdateChapter": "3 nga\u0300y tr\u01b0\u01a1\u0301c"
    },
    {
      "urlChapter": "chapter-68",
      "dateUpdateChapter": "9 nga\u0300y tr\u01b0\u01a1\u0301c"
    },
    {
      "urlChapter": "chapter-67",
      "dateUpdateChapter": "16 nga\u0300y tr\u01b0\u01a1\u0301c"
    },
    {
      "urlChapter": "chapter-66",
      "dateUpdateChapter": "23 nga\u0300y tr\u01b0\u01a1\u0301c"
    },
    {
      "urlChapter": "chapter-65",
      "dateUpdateChapter": "2024-03-02 17:01:10"
    },
    {
      "urlChapter": "chapter-64",
      "dateUpdateChapter": "2024-02-25 10:40:27"
    },
    {
      "urlChapter": "chapter-63",
      "dateUpdateChapter": "2024-02-17 22:09:57"
    },
    {
      "urlChapter": "chapter-62",
      "dateUpdateChapter": "2024-01-29 17:24:38"
    },
    {
      "urlChapter": "chapter-61",
      "dateUpdateChapter": "2024-01-21 08:50:44"
    },
    {
      "urlChapter": "chapter-60",
      "dateUpdateChapter": "2024-01-14 14:52:24"
    },
    {
      "urlChapter": "chapter-59",
      "dateUpdateChapter": "2024-01-07 22:09:06"
    },
    {
      "urlChapter": "chapter-58",
      "dateUpdateChapter": "2023-12-31 08:23:44"
    },
    {
      "urlChapter": "chapter-57",
      "dateUpdateChapter": "2023-12-21 15:06:27"
    },
    {
      "urlChapter": "chapter-56",
      "dateUpdateChapter": "2023-12-21 15:06:24"
    },
    {
      "urlChapter": "chapter-55",
      "dateUpdateChapter": "2023-12-21 15:06:21"
    },
    {
      "urlChapter": "chapter-54",
      "dateUpdateChapter": "2023-12-21 15:06:18"
    },
    {
      "urlChapter": "chapter-53",
      "dateUpdateChapter": "2023-12-21 15:06:15"
    },
    {
      "urlChapter": "chapter-52",
      "dateUpdateChapter": "2023-12-21 15:06:11"
    },
    {
      "urlChapter": "chapter-51",
      "dateUpdateChapter": "2023-12-21 15:06:08"
    },
    {
      "urlChapter": "chapter-50",
      "dateUpdateChapter": "2023-12-21 15:06:05"
    },
    {
      "urlChapter": "chapter-49",
      "dateUpdateChapter": "2023-12-21 15:06:02"
    },
    {
      "urlChapter": "chapter-48",
      "dateUpdateChapter": "2023-12-21 15:06:00"
    },
    {
      "urlChapter": "chapter-47",
      "dateUpdateChapter": "2023-12-21 15:05:57"
    },
    {
      "urlChapter": "chapter-46",
      "dateUpdateChapter": "2023-12-21 15:05:54"
    },
    {
      "urlChapter": "chapter-45",
      "dateUpdateChapter": "2023-12-21 15:05:51"
    },
    {
      "urlChapter": "chapter-44",
      "dateUpdateChapter": "2023-12-21 15:05:47"
    },
    {
      "urlChapter": "chapter-43",
      "dateUpdateChapter": "2023-12-21 15:05:45"
    },
    {
      "urlChapter": "chapter-42",
      "dateUpdateChapter": "2023-12-21 15:05:43"
    },
    {
      "urlChapter": "chapter-41",
      "dateUpdateChapter": "2023-12-21 15:05:41"
    },
    {
      "urlChapter": "chapter-40",
      "dateUpdateChapter": "2023-12-21 15:05:38"
    },
    {
      "urlChapter": "chapter-39",
      "dateUpdateChapter": "2023-12-21 15:05:35"
    },
    {
      "urlChapter": "chapter-38",
      "dateUpdateChapter": "2023-12-21 15:05:32"
    },
    {
      "urlChapter": "chapter-37",
      "dateUpdateChapter": "2023-12-21 15:05:29"
    },
    {
      "urlChapter": "chapter-36",
      "dateUpdateChapter": "2023-12-21 15:05:26"
    },
    {
      "urlChapter": "chapter-35",
      "dateUpdateChapter": "2023-12-21 15:05:24"
    },
    {
      "urlChapter": "chapter-34",
      "dateUpdateChapter": "2023-12-21 15:05:21"
    },
    {
      "urlChapter": "chapter-33",
      "dateUpdateChapter": "2023-12-21 15:05:19"
    },
    {
      "urlChapter": "chapter-32",
      "dateUpdateChapter": "2023-12-21 15:05:16"
    },
    {
      "urlChapter": "chapter-31",
      "dateUpdateChapter": "2023-12-21 15:05:13"
    },
    {
      "urlChapter": "chapter-30",
      "dateUpdateChapter": "2023-12-21 15:05:10"
    },
    {
      "urlChapter": "chapter-29",
      "dateUpdateChapter": "2023-12-21 15:05:07"
    },
    {
      "urlChapter": "chapter-28",
      "dateUpdateChapter": "2023-12-21 15:05:04"
    },
    {
      "urlChapter": "chapter-27",
      "dateUpdateChapter": "2023-12-21 15:05:01"
    },
    {
      "urlChapter": "chapter-26",
      "dateUpdateChapter": "2023-12-21 15:04:58"
    },
    {
      "urlChapter": "chapter-25",
      "dateUpdateChapter": "2023-12-21 15:04:55"
    },
    {
      "urlChapter": "chapter-24",
      "dateUpdateChapter": "2023-12-21 15:04:52"
    },
    {
      "urlChapter": "chapter-23",
      "dateUpdateChapter": "2023-12-21 15:04:49"
    },
    {
      "urlChapter": "chapter-22",
      "dateUpdateChapter": "2023-12-21 15:04:46"
    },
    {
      "urlChapter": "chapter-21",
      "dateUpdateChapter": "2023-12-21 15:04:43"
    },
    {
      "urlChapter": "chapter-20",
      "dateUpdateChapter": "2023-12-21 15:04:40"
    },
    {
      "urlChapter": "chapter-19",
      "dateUpdateChapter": "2023-12-21 15:04:38"
    },
    {
      "urlChapter": "chapter-18",
      "dateUpdateChapter": "2023-12-21 15:04:35"
    },
    {
      "urlChapter": "chapter-17",
      "dateUpdateChapter": "2023-12-21 15:04:33"
    },
    {
      "urlChapter": "chapter-16",
      "dateUpdateChapter": "2023-12-21 15:04:30"
    },
    {
      "urlChapter": "chapter-15",
      "dateUpdateChapter": "2023-12-21 15:04:28"
    },
    {
      "urlChapter": "chapter-14",
      "dateUpdateChapter": "2023-12-21 15:04:26"
    },
    {
      "urlChapter": "chapter-13",
      "dateUpdateChapter": "2023-12-21 15:04:23"
    },
    {
      "urlChapter": "chapter-12",
      "dateUpdateChapter": "2023-12-21 15:04:21"
    },
    {
      "urlChapter": "chapter-11",
      "dateUpdateChapter": "2023-12-21 15:04:18"
    },
    {
      "urlChapter": "chapter-10",
      "dateUpdateChapter": "2023-12-21 15:04:14"
    },
    {
      "urlChapter": "chapter-9",
      "dateUpdateChapter": "2023-12-21 15:04:11"
    },
    {
      "urlChapter": "chapter-8",
      "dateUpdateChapter": "2023-12-21 15:04:08"
    },
    {
      "urlChapter": "chapter-7",
      "dateUpdateChapter": "2023-12-21 15:04:05"
    },
    {
      "urlChapter": "chapter-6",
      "dateUpdateChapter": "2023-12-21 15:04:03"
    },
    {
      "urlChapter": "chapter-5",
      "dateUpdateChapter": "2023-12-21 15:04:00"
    },
    {
      "urlChapter": "chapter-4",
      "dateUpdateChapter": "2023-12-21 15:03:57"
    },
    {
      "urlChapter": "chapter-3",
      "dateUpdateChapter": "2023-12-21 15:03:55"
    },
    {
      "urlChapter": "chapter-2",
      "dateUpdateChapter": "2023-12-21 15:03:52"
    },
    {
      "urlChapter": "chapter-1",
      "dateUpdateChapter": "2023-12-21 15:03:50"
    }
  ]
}