{
  "Title": "Free Short Dou - Rin Matsuoka Colletion",
  "URL": "free-short-dou-rin-matsuoka-colletion",
  "CoverImage": "free-short-dou-rin-matsuoka-colletion.jpg",
  "CreateAt": "25/01/2024",
  "statusComic": 0,
  "Category": [
    "Comedy",
    "Doujinshi",
    "Drama",
    "Ng\u00f4n T\u00ecnh",
    "One shot",
    "Romance",
    "School Life",
    "Shoujo Ai",
    "Shounen"
  ],
  "LastChapter": "chapter-20",
  "TotalChapter": 20,
  "Chapters": {
    "urlChapter": "chapter-20",
    "dateUpdateChapter": "2024-01-25 00:08:21"
  }
}