{
  "Title": "H\u00e0o M\u00f4n Boss Thi\u00ean Gi\u1edbi Th\u00ea",
  "URL": "hao-mon-boss-thien-gioi-the",
  "CoverImage": "hao-mon-boss-thien-gioi-the.jpg",
  "CreateAt": "30/12/2023",
  "statusComic": 0,
  "Category": [
    "Comedy",
    "Manhua",
    "Ng\u00f4n T\u00ecnh",
    "Romance",
    "Shoujo",
    "Smut",
    "Truy\u1ec7n M\u00e0u"
  ],
  "LastChapter": "chapter-127",
  "TotalChapter": 127,
  "Chapters": {
    "urlChapter": "chapter-127",
    "dateUpdateChapter": "2023-12-30 00:31:26"
  }
}