{
  "Title": "H\u00ecnh nh\u01b0 nh\u1eefng \u0111\u1ee9a tr\u1ebb r\u1eafc r\u1ed1i \u0111\u00f3 \u0111\u1ebfn t\u1eeb th\u1ebf gi\u1edbi kh\u00e1c th\u00ec ph\u1ea3i? Z",
  "URL": "hinh-nhu-nhung-dua-tre-rac-roi-do-den-tu-the-gioi-khac-thi-phai-z",
  "CoverImage": "hinh-nhu-nhung-dua-tre-rac-roi-do-den-tu-the-gioi-khac-thi-phai-z.jpg",
  "CreateAt": "14/01/2024",
  "statusComic": 1,
  "Category": [
    "Action",
    "Anime",
    "Comedy",
    "Fantasy",
    "Shounen"
  ],
  "LastChapter": "chapter-15",
  "TotalChapter": 15,
  "Chapters": {
    "urlChapter": "chapter-15",
    "dateUpdateChapter": "2024-01-14 10:09:48"
  }
}