{
  "Title": "Hirasaka Hinako ga Ero Kawaii koto wo Ore dake ga Shitteiru",
  "URL": "hirasaka-hinako-ga-ero-kawaii-koto-wo-ore-dake-ga-shitteiru",
  "CoverImage": "hirasaka-hinako-ga-ero-kawaii-koto-wo-ore-dake-ga-shitteiru.jpg",
  "CreateAt": "26/12/2023",
  "statusComic": 0,
  "Category": [
    "Ecchi",
    "Manga",
    "Romance",
    "School Life",
    "Shounen",
    "Supernatural"
  ],
  "LastChapter": "chapter-48",
  "TotalChapter": 48,
  "Chapters": {
    "urlChapter": "chapter-48",
    "dateUpdateChapter": "2023-12-26 21:26:36"
  }
}