{
  "Title": "Hotboy qu\u1ed1c d\u00e2n s\u1ee7ng th\u00e0nh nghi\u1ec7n",
  "URL": "hotboy-quoc-dan-sung-thanh-nghien",
  "CoverImage": "hotboy-quoc-dan-sung-thanh-nghien.jpg",
  "CreateAt": "16/01/2024",
  "statusComic": 0,
  "Category": [
    "Comedy",
    "Manhua",
    "Ng\u00f4n T\u00ecnh",
    "Romance",
    "Shoujo",
    "Truy\u1ec7n M\u00e0u"
  ],
  "LastChapter": "chapter-6",
  "TotalChapter": 6,
  "Chapters": {
    "urlChapter": "chapter-6",
    "dateUpdateChapter": "2024-01-16 22:52:05"
  }
}