{
  "Title": "H\u01b0\u1edbng H\u1eafc H\u00f3a T\u1ed5ng T\u00e0i Hi\u1ebfn Th\u01b0\u1ee3ng Sa",
  "URL": "huong-hac-hoa-tong-tai-hien-thuong-sa",
  "CoverImage": "huong-hac-hoa-tong-tai-hien-thuong-sa.jpg",
  "CreateAt": "02/02/2024",
  "statusComic": 0,
  "Category": [
    "Chuy\u1ec3n Sinh",
    "Manhua",
    "Ng\u00f4n T\u00ecnh",
    "Romance",
    "Truy\u1ec7n M\u00e0u"
  ],
  "LastChapter": "chapter-1",
  "TotalChapter": 1,
  "Chapters": {
    "urlChapter": "chapter-1",
    "dateUpdateChapter": "2024-02-02 13:58:54"
  }
}