{
  "Title": "K\u1ebf Ho\u1ea1ch Tr\u1ea3 Th\u00f9 C\u1ee7a \u0110\u00edch N\u1eef Tr\u1ecdng Sinh",
  "URL": "ke-hoach-tra-thu-cua-dich-nu-trong-sinh",
  "CoverImage": "ke-hoach-tra-thu-cua-dich-nu-trong-sinh.jpg",
  "CreateAt": "26/01/2024",
  "statusComic": 0,
  "Category": [
    "Chuy\u1ec3n Sinh",
    "C\u1ed5 \u0110\u1ea1i",
    "Drama",
    "Manhua",
    "Ng\u00f4n T\u00ecnh",
    "Truy\u1ec7n M\u00e0u"
  ],
  "LastChapter": "chapter-7",
  "TotalChapter": 7,
  "Chapters": {
    "urlChapter": "chapter-7",
    "dateUpdateChapter": "2024-01-26 07:59:58"
  }
}