{
  "Title": "K\u1ebf Ho\u1ea1ch T\u00ecnh Y\u00eau Trong S\u00e1ng",
  "URL": "ke-hoach-tinh-yeu-trong-sang",
  "CoverImage": "ke-hoach-tinh-yeu-trong-sang.jpg",
  "CreateAt": "16/12/2023",
  "statusComic": 0,
  "Category": [
    "Comedy",
    "Manhwa",
    "Ng\u00f4n T\u00ecnh",
    "Romance",
    "School Life",
    "Truy\u1ec7n M\u00e0u"
  ],
  "LastChapter": "chapter-106",
  "TotalChapter": 106,
  "Chapters": {
    "urlChapter": "chapter-106",
    "dateUpdateChapter": "2023-12-16 09:06:24"
  }
}