{
  "Title": "Living in this world with Cut & Paste",
  "URL": "living-in-this-world-with-cut-paste",
  "CoverImage": "living-in-this-world-with-cut-paste.jpg",
  "CreateAt": "03/01/2024",
  "statusComic": 0,
  "Category": [
    "Action",
    "Adventure",
    "Comedy",
    "Ecchi",
    "Fantasy",
    "Manga",
    "Seinen",
    "Slice of Life"
  ],
  "LastChapter": "chapter-21",
  "TotalChapter": 21,
  "Chapters": {
    "urlChapter": "chapter-21",
    "dateUpdateChapter": "2024-01-03 09:18:16"
  }
}