{
  "Title": "Ma V\u01b0\u01a1ng \u0110\u1ea1i Nh\u00e2n, Phu Nh\u00e2n L\u1ea1i B\u1ecf \u0110i R\u1ed3i!",
  "URL": "ma-vuong-dai-nhan-phu-nhan-lai-bo-di-roi",
  "CoverImage": "ma-vuong-dai-nhan-phu-nhan-lai-bo-di-roi.jpg",
  "CreateAt": "26/12/2023",
  "statusComic": 0,
  "Category": [
    "Comedy",
    "Manhua",
    "Ng\u00f4n T\u00ecnh",
    "Romance",
    "Shounen",
    "Truy\u1ec7n M\u00e0u"
  ],
  "LastChapter": "chapter-70",
  "TotalChapter": 70,
  "Chapters": {
    "urlChapter": "chapter-70",
    "dateUpdateChapter": "2023-12-26 21:47:23"
  }
}