{
  "Title": "N\u00e0ng C\u00f4ng Ch\u00faa C\u1ee7a M\u1ecdi Ng\u01b0\u1eddi",
  "URL": "nang-cong-chua-cua-moi-nguoi",
  "CoverImage": "nang-cong-chua-cua-moi-nguoi.jpg",
  "CreateAt": "31/12/2023",
  "statusComic": 0,
  "Category": [
    "Chuy\u1ec3n Sinh",
    "C\u1ed5 \u0110\u1ea1i",
    "Manhwa",
    "Ng\u00f4n T\u00ecnh",
    "Romance",
    "Truy\u1ec7n M\u00e0u"
  ],
  "LastChapter": "chapter-37",
  "TotalChapter": 37,
  "Chapters": [
    {
      "urlChapter": "chapter-37",
      "dateUpdateChapter": "2023-12-31 15:04:34"
    },
    {
      "urlChapter": "chapter-36",
      "dateUpdateChapter": "2023-12-31 15:04:31"
    },
    {
      "urlChapter": "chapter-35",
      "dateUpdateChapter": "2023-12-31 15:04:28"
    },
    {
      "urlChapter": "chapter-34",
      "dateUpdateChapter": "2023-12-31 15:04:24"
    },
    {
      "urlChapter": "chapter-33",
      "dateUpdateChapter": "2023-12-31 15:04:21"
    },
    {
      "urlChapter": "chapter-32",
      "dateUpdateChapter": "2023-12-31 15:04:17"
    },
    {
      "urlChapter": "chapter-31",
      "dateUpdateChapter": "2023-12-31 15:04:13"
    },
    {
      "urlChapter": "chapter-30",
      "dateUpdateChapter": "2023-12-31 15:04:09"
    },
    {
      "urlChapter": "chapter-29",
      "dateUpdateChapter": "2023-12-31 15:04:06"
    },
    {
      "urlChapter": "chapter-28",
      "dateUpdateChapter": "2023-12-31 15:04:03"
    },
    {
      "urlChapter": "chapter-27",
      "dateUpdateChapter": "2023-12-31 15:04:00"
    },
    {
      "urlChapter": "chapter-26",
      "dateUpdateChapter": "2023-12-31 15:03:57"
    },
    {
      "urlChapter": "chapter-25",
      "dateUpdateChapter": "2023-12-31 15:03:54"
    },
    {
      "urlChapter": "chapter-24",
      "dateUpdateChapter": "2023-12-31 15:03:50"
    },
    {
      "urlChapter": "chapter-23",
      "dateUpdateChapter": "2023-12-31 15:03:46"
    },
    {
      "urlChapter": "chapter-22",
      "dateUpdateChapter": "2023-12-31 15:03:43"
    },
    {
      "urlChapter": "chapter-21",
      "dateUpdateChapter": "2023-12-31 15:03:39"
    },
    {
      "urlChapter": "chapter-20",
      "dateUpdateChapter": "2023-12-31 15:03:35"
    },
    {
      "urlChapter": "chapter-19",
      "dateUpdateChapter": "2023-12-31 15:03:32"
    },
    {
      "urlChapter": "chapter-18",
      "dateUpdateChapter": "2023-12-31 15:03:29"
    },
    {
      "urlChapter": "chapter-17",
      "dateUpdateChapter": "2023-12-31 15:03:25"
    },
    {
      "urlChapter": "chapter-16",
      "dateUpdateChapter": "2023-12-31 15:03:21"
    },
    {
      "urlChapter": "chapter-15",
      "dateUpdateChapter": "2023-12-31 15:03:17"
    },
    {
      "urlChapter": "chapter-14",
      "dateUpdateChapter": "2023-12-31 15:03:13"
    },
    {
      "urlChapter": "chapter-13",
      "dateUpdateChapter": "2023-12-31 15:03:10"
    },
    {
      "urlChapter": "chapter-12",
      "dateUpdateChapter": "2023-12-31 15:03:07"
    },
    {
      "urlChapter": "chapter-11",
      "dateUpdateChapter": "2023-12-31 15:03:04"
    },
    {
      "urlChapter": "chapter-10",
      "dateUpdateChapter": "2023-12-31 15:03:01"
    },
    {
      "urlChapter": "chapter-9",
      "dateUpdateChapter": "2023-12-31 15:02:58"
    },
    {
      "urlChapter": "chapter-8",
      "dateUpdateChapter": "2023-12-31 15:02:55"
    },
    {
      "urlChapter": "chapter-7",
      "dateUpdateChapter": "2023-12-31 15:02:51"
    },
    {
      "urlChapter": "chapter-6",
      "dateUpdateChapter": "2023-12-31 15:02:48"
    },
    {
      "urlChapter": "chapter-5",
      "dateUpdateChapter": "2023-12-31 15:02:45"
    },
    {
      "urlChapter": "chapter-4",
      "dateUpdateChapter": "2023-12-31 15:02:42"
    },
    {
      "urlChapter": "chapter-3",
      "dateUpdateChapter": "2023-12-31 15:02:38"
    },
    {
      "urlChapter": "chapter-2",
      "dateUpdateChapter": "2023-12-31 15:02:35"
    },
    {
      "urlChapter": "chapter-1",
      "dateUpdateChapter": "2023-12-31 15:02:32"
    }
  ]
}