{
  "Title": "N\u1ebfu L\u00e0 Ph\u1ea3n Di\u1ec7n, Li\u1ec7u T\u00f4i S\u1ebd Ch\u1ebft?",
  "URL": "neu-la-phan-dien-lieu-toi-se-chet",
  "CoverImage": "neu-la-phan-dien-lieu-toi-se-chet.jpg",
  "CreateAt": "21/12/2023",
  "statusComic": 0,
  "Category": [
    "C\u1ed5 \u0110\u1ea1i",
    "Drama",
    "Manhwa",
    "Ng\u00f4n T\u00ecnh",
    "Shoujo",
    "Truy\u1ec7n M\u00e0u"
  ],
  "LastChapter": "chapter-61",
  "TotalChapter": 61,
  "Chapters": {
    "urlChapter": "chapter-61",
    "dateUpdateChapter": "2024-01-16 08:16:18"
  }
}