{
  "Title": "Ng\u1eafm Nh\u00ecn \u0110i\u1ec1u Tuy\u1ec7t V\u1eddi Nh\u1ea5t",
  "URL": "ngam-nhin-dieu-tuyet-voi-nhat",
  "CoverImage": "ngam-nhin-dieu-tuyet-voi-nhat.jpg",
  "CreateAt": "16/01/2024",
  "statusComic": 0,
  "Category": [
    "Manhwa",
    "Ng\u00f4n T\u00ecnh",
    "Romance",
    "School Life",
    "Truy\u1ec7n M\u00e0u",
    "Webtoon"
  ],
  "LastChapter": "chapter-35",
  "TotalChapter": 35,
  "Chapters": {
    "urlChapter": "chapter-35",
    "dateUpdateChapter": "2024-01-16 16:32:16"
  }
}