{
  "Title": "N\u1ee5 C\u01b0\u1eddi C\u1ee7a Ng\u01b0\u01a1i Ng\u1ecdt \u0110\u1ebfn M\u1ee9c L\u00e0m G\u00e3y T\u00e1m C\u00e1i R\u0103ng C\u1ee7a Ta",
  "URL": "nu-cuoi-cua-nguoi-ngot-den-muc-lam-gay-tam-cai-rang-cua-ta",
  "CoverImage": "nu-cuoi-cua-nguoi-ngot-den-muc-lam-gay-tam-cai-rang-cua-ta.jpg",
  "CreateAt": "25/12/2023",
  "statusComic": 0,
  "Category": [
    "C\u1ed5 \u0110\u1ea1i",
    "Ng\u00f4n T\u00ecnh",
    "Xuy\u00ean Kh\u00f4ng"
  ],
  "LastChapter": "chapter-103",
  "TotalChapter": 103,
  "Chapters": [
    {
      "urlChapter": "chapter-103",
      "dateUpdateChapter": "5 nga\u0300y tr\u01b0\u01a1\u0301c"
    },
    {
      "urlChapter": "chapter-102",
      "dateUpdateChapter": "5 nga\u0300y tr\u01b0\u01a1\u0301c"
    },
    {
      "urlChapter": "chapter-101",
      "dateUpdateChapter": "21 nga\u0300y tr\u01b0\u01a1\u0301c"
    },
    {
      "urlChapter": "chapter-100",
      "dateUpdateChapter": "21 nga\u0300y tr\u01b0\u01a1\u0301c"
    },
    {
      "urlChapter": "chapter-99",
      "dateUpdateChapter": "2023-12-25 15:40:16"
    },
    {
      "urlChapter": "chapter-98",
      "dateUpdateChapter": "2023-12-25 15:40:14"
    },
    {
      "urlChapter": "chapter-97",
      "dateUpdateChapter": "2023-12-25 15:40:13"
    },
    {
      "urlChapter": "chapter-96",
      "dateUpdateChapter": "2023-12-25 15:40:11"
    },
    {
      "urlChapter": "chapter-95",
      "dateUpdateChapter": "2023-12-25 15:40:09"
    },
    {
      "urlChapter": "chapter-94",
      "dateUpdateChapter": "2023-12-25 15:40:07"
    },
    {
      "urlChapter": "chapter-93",
      "dateUpdateChapter": "2023-12-25 15:40:05"
    },
    {
      "urlChapter": "chapter-92",
      "dateUpdateChapter": "2023-12-25 15:40:04"
    },
    {
      "urlChapter": "chapter-91",
      "dateUpdateChapter": "2023-12-25 15:40:02"
    },
    {
      "urlChapter": "chapter-90",
      "dateUpdateChapter": "2023-12-25 15:39:59"
    },
    {
      "urlChapter": "chapter-89",
      "dateUpdateChapter": "2023-12-25 15:39:58"
    },
    {
      "urlChapter": "chapter-88",
      "dateUpdateChapter": "2023-12-25 15:39:56"
    },
    {
      "urlChapter": "chapter-87",
      "dateUpdateChapter": "2023-12-25 15:39:54"
    },
    {
      "urlChapter": "chapter-86",
      "dateUpdateChapter": "2023-12-25 15:39:52"
    },
    {
      "urlChapter": "chapter-85",
      "dateUpdateChapter": "2023-12-25 15:39:51"
    },
    {
      "urlChapter": "chapter-84",
      "dateUpdateChapter": "2023-12-25 15:39:49"
    },
    {
      "urlChapter": "chapter-83",
      "dateUpdateChapter": "2023-12-25 15:39:48"
    },
    {
      "urlChapter": "chapter-82",
      "dateUpdateChapter": "2023-12-25 15:39:46"
    },
    {
      "urlChapter": "chapter-81",
      "dateUpdateChapter": "2023-12-25 15:39:44"
    },
    {
      "urlChapter": "chapter-80",
      "dateUpdateChapter": "2023-12-25 15:39:42"
    },
    {
      "urlChapter": "chapter-79",
      "dateUpdateChapter": "2023-12-25 15:39:39"
    },
    {
      "urlChapter": "chapter-78",
      "dateUpdateChapter": "2023-12-25 15:39:38"
    },
    {
      "urlChapter": "chapter-77",
      "dateUpdateChapter": "2023-12-25 15:39:36"
    },
    {
      "urlChapter": "chapter-76",
      "dateUpdateChapter": "2023-12-25 15:39:35"
    },
    {
      "urlChapter": "chapter-75",
      "dateUpdateChapter": "2023-12-25 15:39:33"
    },
    {
      "urlChapter": "chapter-74",
      "dateUpdateChapter": "2023-12-25 15:39:32"
    },
    {
      "urlChapter": "chapter-73",
      "dateUpdateChapter": "2023-12-25 15:39:30"
    },
    {
      "urlChapter": "chapter-72",
      "dateUpdateChapter": "2023-12-25 15:39:29"
    },
    {
      "urlChapter": "chapter-71",
      "dateUpdateChapter": "2023-12-25 15:39:27"
    },
    {
      "urlChapter": "chapter-70",
      "dateUpdateChapter": "2023-12-25 15:39:26"
    },
    {
      "urlChapter": "chapter-69",
      "dateUpdateChapter": "2023-12-25 15:39:24"
    },
    {
      "urlChapter": "chapter-68",
      "dateUpdateChapter": "2023-12-25 15:39:22"
    },
    {
      "urlChapter": "chapter-67",
      "dateUpdateChapter": "2023-12-25 15:39:20"
    },
    {
      "urlChapter": "chapter-66",
      "dateUpdateChapter": "2023-12-25 15:39:19"
    },
    {
      "urlChapter": "chapter-65",
      "dateUpdateChapter": "2023-12-25 15:39:18"
    },
    {
      "urlChapter": "chapter-64",
      "dateUpdateChapter": "2023-12-25 15:39:16"
    },
    {
      "urlChapter": "chapter-63",
      "dateUpdateChapter": "2023-12-25 15:39:15"
    },
    {
      "urlChapter": "chapter-62",
      "dateUpdateChapter": "2023-12-25 15:39:13"
    },
    {
      "urlChapter": "chapter-61",
      "dateUpdateChapter": "2023-12-25 15:39:11"
    },
    {
      "urlChapter": "chapter-60",
      "dateUpdateChapter": "2023-12-25 15:39:10"
    },
    {
      "urlChapter": "chapter-59",
      "dateUpdateChapter": "2023-12-25 15:39:08"
    },
    {
      "urlChapter": "chapter-58",
      "dateUpdateChapter": "2023-12-25 15:39:07"
    },
    {
      "urlChapter": "chapter-57",
      "dateUpdateChapter": "2023-12-25 15:39:05"
    },
    {
      "urlChapter": "chapter-56",
      "dateUpdateChapter": "2023-12-25 15:39:01"
    },
    {
      "urlChapter": "chapter-55",
      "dateUpdateChapter": "2023-12-25 15:38:59"
    },
    {
      "urlChapter": "chapter-54",
      "dateUpdateChapter": "2023-12-25 15:38:57"
    },
    {
      "urlChapter": "chapter-53",
      "dateUpdateChapter": "2023-12-25 15:38:55"
    },
    {
      "urlChapter": "chapter-52",
      "dateUpdateChapter": "2023-12-25 15:38:53"
    },
    {
      "urlChapter": "chapter-51",
      "dateUpdateChapter": "2023-12-25 15:38:51"
    },
    {
      "urlChapter": "chapter-50",
      "dateUpdateChapter": "2023-12-25 15:38:50"
    },
    {
      "urlChapter": "chapter-49",
      "dateUpdateChapter": "2023-12-25 15:38:44"
    },
    {
      "urlChapter": "chapter-48",
      "dateUpdateChapter": "2023-12-25 15:38:41"
    },
    {
      "urlChapter": "chapter-47",
      "dateUpdateChapter": "2023-12-25 15:38:40"
    },
    {
      "urlChapter": "chapter-46",
      "dateUpdateChapter": "2023-12-25 15:38:38"
    },
    {
      "urlChapter": "chapter-45",
      "dateUpdateChapter": "2023-12-25 15:38:37"
    },
    {
      "urlChapter": "chapter-44",
      "dateUpdateChapter": "2023-12-25 15:38:35"
    },
    {
      "urlChapter": "chapter-43",
      "dateUpdateChapter": "2023-12-25 15:38:33"
    },
    {
      "urlChapter": "chapter-42",
      "dateUpdateChapter": "2023-12-25 15:38:32"
    },
    {
      "urlChapter": "chapter-41",
      "dateUpdateChapter": "2023-12-25 15:38:30"
    },
    {
      "urlChapter": "chapter-40",
      "dateUpdateChapter": "2023-12-25 15:38:28"
    },
    {
      "urlChapter": "chapter-39",
      "dateUpdateChapter": "2023-12-25 15:38:26"
    },
    {
      "urlChapter": "chapter-38",
      "dateUpdateChapter": "2023-12-25 15:38:25"
    },
    {
      "urlChapter": "chapter-37",
      "dateUpdateChapter": "2023-12-25 15:38:24"
    },
    {
      "urlChapter": "chapter-36",
      "dateUpdateChapter": "2023-12-25 15:38:21"
    },
    {
      "urlChapter": "chapter-35",
      "dateUpdateChapter": "2023-12-25 15:38:19"
    },
    {
      "urlChapter": "chapter-34",
      "dateUpdateChapter": "2023-12-25 15:38:17"
    },
    {
      "urlChapter": "chapter-33",
      "dateUpdateChapter": "2023-12-25 15:38:14"
    },
    {
      "urlChapter": "chapter-32",
      "dateUpdateChapter": "2023-12-25 15:38:13"
    },
    {
      "urlChapter": "chapter-31",
      "dateUpdateChapter": "2023-12-25 15:38:11"
    },
    {
      "urlChapter": "chapter-30",
      "dateUpdateChapter": "2023-12-25 15:38:09"
    },
    {
      "urlChapter": "chapter-29",
      "dateUpdateChapter": "2023-12-25 15:38:07"
    },
    {
      "urlChapter": "chapter-28",
      "dateUpdateChapter": "2023-12-25 15:38:05"
    },
    {
      "urlChapter": "chapter-27",
      "dateUpdateChapter": "2023-12-25 15:37:54"
    },
    {
      "urlChapter": "chapter-26",
      "dateUpdateChapter": "2023-12-25 15:37:49"
    },
    {
      "urlChapter": "chapter-25",
      "dateUpdateChapter": "2023-12-25 15:37:47"
    },
    {
      "urlChapter": "chapter-24",
      "dateUpdateChapter": "2023-12-25 15:37:45"
    },
    {
      "urlChapter": "chapter-23",
      "dateUpdateChapter": "2023-12-25 15:37:44"
    },
    {
      "urlChapter": "chapter-22",
      "dateUpdateChapter": "2023-12-25 15:37:41"
    },
    {
      "urlChapter": "chapter-21",
      "dateUpdateChapter": "2023-12-25 15:37:40"
    },
    {
      "urlChapter": "chapter-20",
      "dateUpdateChapter": "2023-12-25 15:37:38"
    },
    {
      "urlChapter": "chapter-19",
      "dateUpdateChapter": "2023-12-25 15:37:36"
    },
    {
      "urlChapter": "chapter-18",
      "dateUpdateChapter": "2023-12-25 15:37:35"
    },
    {
      "urlChapter": "chapter-17",
      "dateUpdateChapter": "2023-12-25 15:37:34"
    },
    {
      "urlChapter": "chapter-16",
      "dateUpdateChapter": "2023-12-25 15:37:33"
    },
    {
      "urlChapter": "chapter-15",
      "dateUpdateChapter": "2023-12-25 15:37:31"
    },
    {
      "urlChapter": "chapter-14",
      "dateUpdateChapter": "2023-12-25 15:37:29"
    },
    {
      "urlChapter": "chapter-13",
      "dateUpdateChapter": "2023-12-25 15:37:27"
    },
    {
      "urlChapter": "chapter-12",
      "dateUpdateChapter": "2023-12-25 15:37:26"
    },
    {
      "urlChapter": "chapter-11",
      "dateUpdateChapter": "2023-12-25 15:37:24"
    },
    {
      "urlChapter": "chapter-10",
      "dateUpdateChapter": "2023-12-25 15:37:22"
    },
    {
      "urlChapter": "chapter-9",
      "dateUpdateChapter": "2023-12-25 15:37:21"
    },
    {
      "urlChapter": "chapter-8",
      "dateUpdateChapter": "2023-12-25 15:37:20"
    },
    {
      "urlChapter": "chapter-7",
      "dateUpdateChapter": "2023-12-25 15:37:18"
    },
    {
      "urlChapter": "chapter-6",
      "dateUpdateChapter": "2023-12-25 15:37:17"
    },
    {
      "urlChapter": "chapter-5",
      "dateUpdateChapter": "2023-12-25 15:37:14"
    },
    {
      "urlChapter": "chapter-4",
      "dateUpdateChapter": "2023-12-25 15:37:13"
    },
    {
      "urlChapter": "chapter-3",
      "dateUpdateChapter": "2023-12-25 15:37:11"
    },
    {
      "urlChapter": "chapter-2",
      "dateUpdateChapter": "2023-12-25 15:37:10"
    },
    {
      "urlChapter": "chapter-1",
      "dateUpdateChapter": "2023-12-25 15:37:09"
    }
  ]
}