{
  "Title": "Ta C\u00f3 M\u1ed9t S\u01a1n Tr\u1ea1i",
  "URL": "ta-co-mot-son-trai",
  "CoverImage": "ta-co-mot-son-trai.jpg",
  "CreateAt": "06/12/2023",
  "statusComic": 0,
  "Category": [
    "Action",
    "Chuy\u1ec3n Sinh",
    "Fantasy",
    "Manhua",
    "Truy\u1ec7n M\u00e0u"
  ],
  "LastChapter": "chapter-849",
  "TotalChapter": 850,
  "Chapters": [
    {
      "urlChapter": "chapter-849",
      "dateUpdateChapter": "1 gi\u01a1\u0300 tr\u01b0\u01a1\u0301c"
    },
    {
      "urlChapter": "chapter-848",
      "dateUpdateChapter": "1 nga\u0300y tr\u01b0\u01a1\u0301c"
    },
    {
      "urlChapter": "chapter-847",
      "dateUpdateChapter": "3 nga\u0300y tr\u01b0\u01a1\u0301c"
    },
    {
      "urlChapter": "chapter-846",
      "dateUpdateChapter": "4 nga\u0300y tr\u01b0\u01a1\u0301c"
    },
    {
      "urlChapter": "chapter-845",
      "dateUpdateChapter": "6 nga\u0300y tr\u01b0\u01a1\u0301c"
    },
    {
      "urlChapter": "chapter-844",
      "dateUpdateChapter": "6 nga\u0300y tr\u01b0\u01a1\u0301c"
    },
    {
      "urlChapter": "chapter-843",
      "dateUpdateChapter": "10 nga\u0300y tr\u01b0\u01a1\u0301c"
    },
    {
      "urlChapter": "chapter-842",
      "dateUpdateChapter": "12 nga\u0300y tr\u01b0\u01a1\u0301c"
    },
    {
      "urlChapter": "chapter-841",
      "dateUpdateChapter": "13 nga\u0300y tr\u01b0\u01a1\u0301c"
    },
    {
      "urlChapter": "chapter-840",
      "dateUpdateChapter": "14 nga\u0300y tr\u01b0\u01a1\u0301c"
    },
    {
      "urlChapter": "chapter-839",
      "dateUpdateChapter": "14 nga\u0300y tr\u01b0\u01a1\u0301c"
    },
    {
      "urlChapter": "chapter-838",
      "dateUpdateChapter": "20 nga\u0300y tr\u01b0\u01a1\u0301c"
    },
    {
      "urlChapter": "chapter-837",
      "dateUpdateChapter": "21 nga\u0300y tr\u01b0\u01a1\u0301c"
    },
    {
      "urlChapter": "chapter-836",
      "dateUpdateChapter": "22 nga\u0300y tr\u01b0\u01a1\u0301c"
    },
    {
      "urlChapter": "chapter-835",
      "dateUpdateChapter": "25 nga\u0300y tr\u01b0\u01a1\u0301c"
    },
    {
      "urlChapter": "chapter-834",
      "dateUpdateChapter": "25 nga\u0300y tr\u01b0\u01a1\u0301c"
    },
    {
      "urlChapter": "chapter-833",
      "dateUpdateChapter": "26 nga\u0300y tr\u01b0\u01a1\u0301c"
    },
    {
      "urlChapter": "chapter-832",
      "dateUpdateChapter": "27 nga\u0300y tr\u01b0\u01a1\u0301c"
    },
    {
      "urlChapter": "chapter-831",
      "dateUpdateChapter": "29 nga\u0300y tr\u01b0\u01a1\u0301c"
    },
    {
      "urlChapter": "chapter-830",
      "dateUpdateChapter": "29 nga\u0300y tr\u01b0\u01a1\u0301c"
    },
    {
      "urlChapter": "chapter-829",
      "dateUpdateChapter": "2024-03-01 10:45:05"
    },
    {
      "urlChapter": "chapter-828",
      "dateUpdateChapter": "2024-02-29 14:13:51"
    },
    {
      "urlChapter": "chapter-827",
      "dateUpdateChapter": "2024-02-27 12:15:05"
    },
    {
      "urlChapter": "chapter-826",
      "dateUpdateChapter": "2024-02-27 12:15:03"
    },
    {
      "urlChapter": "chapter-825",
      "dateUpdateChapter": "2024-02-23 13:45:39"
    },
    {
      "urlChapter": "chapter-824",
      "dateUpdateChapter": "2024-02-23 13:45:37"
    },
    {
      "urlChapter": "chapter-823",
      "dateUpdateChapter": "2024-02-22 09:00:39"
    },
    {
      "urlChapter": "chapter-823",
      "dateUpdateChapter": "2024-02-22 09:00:39"
    },
    {
      "urlChapter": "chapter-822",
      "dateUpdateChapter": "2024-02-22 00:06:24"
    },
    {
      "urlChapter": "chapter-821",
      "dateUpdateChapter": "2024-02-22 00:06:23"
    },
    {
      "urlChapter": "chapter-820",
      "dateUpdateChapter": "2024-02-19 12:56:37"
    },
    {
      "urlChapter": "chapter-819",
      "dateUpdateChapter": "2024-02-18 06:36:06"
    },
    {
      "urlChapter": "chapter-818",
      "dateUpdateChapter": "2024-02-17 06:52:06"
    },
    {
      "urlChapter": "chapter-817",
      "dateUpdateChapter": "2024-02-15 13:12:49"
    },
    {
      "urlChapter": "chapter-816",
      "dateUpdateChapter": "2024-02-14 21:56:48"
    },
    {
      "urlChapter": "chapter-815",
      "dateUpdateChapter": "2024-02-14 06:54:53"
    },
    {
      "urlChapter": "chapter-814",
      "dateUpdateChapter": "2024-02-13 05:32:12"
    },
    {
      "urlChapter": "chapter-813",
      "dateUpdateChapter": "2024-02-12 07:38:58"
    },
    {
      "urlChapter": "chapter-812",
      "dateUpdateChapter": "2024-02-12 07:38:56"
    },
    {
      "urlChapter": "chapter-811",
      "dateUpdateChapter": "2024-02-07 14:48:21"
    },
    {
      "urlChapter": "chapter-810",
      "dateUpdateChapter": "2024-02-07 06:45:11"
    },
    {
      "urlChapter": "chapter-809",
      "dateUpdateChapter": "2024-02-06 09:36:13"
    },
    {
      "urlChapter": "chapter-808",
      "dateUpdateChapter": "2024-02-02 13:54:02"
    },
    {
      "urlChapter": "chapter-807",
      "dateUpdateChapter": "2024-02-02 07:39:50"
    },
    {
      "urlChapter": "chapter-806",
      "dateUpdateChapter": "2024-01-31 13:20:13"
    },
    {
      "urlChapter": "chapter-805",
      "dateUpdateChapter": "2024-01-30 21:52:52"
    },
    {
      "urlChapter": "chapter-804",
      "dateUpdateChapter": "2024-01-29 17:05:01"
    },
    {
      "urlChapter": "chapter-803",
      "dateUpdateChapter": "2024-01-26 19:08:51"
    },
    {
      "urlChapter": "chapter-802",
      "dateUpdateChapter": "2024-01-25 20:09:27"
    },
    {
      "urlChapter": "chapter-801",
      "dateUpdateChapter": "2024-01-24 22:10:27"
    },
    {
      "urlChapter": "chapter-800",
      "dateUpdateChapter": "2024-01-23 14:17:15"
    },
    {
      "urlChapter": "chapter-799",
      "dateUpdateChapter": "2024-01-22 13:31:26"
    },
    {
      "urlChapter": "chapter-798",
      "dateUpdateChapter": "2024-01-19 20:13:12"
    },
    {
      "urlChapter": "chapter-797",
      "dateUpdateChapter": "2024-01-19 20:13:09"
    },
    {
      "urlChapter": "chapter-796",
      "dateUpdateChapter": "2024-01-17 13:04:37"
    },
    {
      "urlChapter": "chapter-795",
      "dateUpdateChapter": "2024-01-17 13:04:36"
    },
    {
      "urlChapter": "chapter-794",
      "dateUpdateChapter": "2024-01-16 07:56:49"
    },
    {
      "urlChapter": "chapter-793",
      "dateUpdateChapter": "2024-01-14 14:32:51"
    },
    {
      "urlChapter": "chapter-792",
      "dateUpdateChapter": "2024-01-14 14:32:49"
    },
    {
      "urlChapter": "chapter-791",
      "dateUpdateChapter": "2024-01-11 15:23:31"
    },
    {
      "urlChapter": "chapter-790",
      "dateUpdateChapter": "2024-01-10 08:05:12"
    },
    {
      "urlChapter": "chapter-789",
      "dateUpdateChapter": "2024-01-08 17:45:17"
    },
    {
      "urlChapter": "chapter-788",
      "dateUpdateChapter": "2024-01-07 21:41:17"
    },
    {
      "urlChapter": "chapter-787",
      "dateUpdateChapter": "2024-01-05 07:44:05"
    },
    {
      "urlChapter": "chapter-786",
      "dateUpdateChapter": "2024-01-03 15:09:02"
    },
    {
      "urlChapter": "chapter-785",
      "dateUpdateChapter": "2024-01-03 15:09:00"
    },
    {
      "urlChapter": "chapter-784",
      "dateUpdateChapter": "2024-01-02 01:13:54"
    },
    {
      "urlChapter": "chapter-783",
      "dateUpdateChapter": "2023-12-30 08:18:57"
    },
    {
      "urlChapter": "chapter-782",
      "dateUpdateChapter": "2023-12-30 08:18:55"
    },
    {
      "urlChapter": "chapter-781",
      "dateUpdateChapter": "2023-12-28 07:20:03"
    },
    {
      "urlChapter": "chapter-780",
      "dateUpdateChapter": "2023-12-27 13:41:56"
    },
    {
      "urlChapter": "chapter-779",
      "dateUpdateChapter": "2023-12-26 08:24:31"
    },
    {
      "urlChapter": "chapter-778",
      "dateUpdateChapter": "2023-12-22 17:20:08"
    },
    {
      "urlChapter": "chapter-777",
      "dateUpdateChapter": "2023-12-22 08:21:10"
    },
    {
      "urlChapter": "chapter-776",
      "dateUpdateChapter": "2023-12-21 05:45:16"
    },
    {
      "urlChapter": "chapter-775",
      "dateUpdateChapter": "2023-12-19 19:07:02"
    },
    {
      "urlChapter": "chapter-774",
      "dateUpdateChapter": "2023-12-18 12:58:19"
    },
    {
      "urlChapter": "chapter-773",
      "dateUpdateChapter": "2023-12-15 13:28:38"
    },
    {
      "urlChapter": "chapter-772",
      "dateUpdateChapter": "2023-12-15 13:28:36"
    },
    {
      "urlChapter": "chapter-771",
      "dateUpdateChapter": "2023-12-13 22:13:27"
    },
    {
      "urlChapter": "chapter-770",
      "dateUpdateChapter": "2023-12-13 22:13:25"
    },
    {
      "urlChapter": "chapter-769",
      "dateUpdateChapter": "2023-12-12 07:21:41"
    },
    {
      "urlChapter": "chapter-768",
      "dateUpdateChapter": "2023-12-09 07:39:35"
    },
    {
      "urlChapter": "chapter-767",
      "dateUpdateChapter": "2023-12-07 18:16:17"
    },
    {
      "urlChapter": "chapter-766",
      "dateUpdateChapter": "2023-12-06 19:56:43"
    },
    {
      "urlChapter": "chapter-765",
      "dateUpdateChapter": "2023-12-06 07:41:11"
    },
    {
      "urlChapter": "chapter-764",
      "dateUpdateChapter": "2023-12-06 07:41:09"
    },
    {
      "urlChapter": "chapter-763",
      "dateUpdateChapter": "2023-12-06 07:41:07"
    },
    {
      "urlChapter": "chapter-762",
      "dateUpdateChapter": "2023-12-06 07:41:04"
    },
    {
      "urlChapter": "chapter-761",
      "dateUpdateChapter": "2023-12-06 07:41:02"
    },
    {
      "urlChapter": "chapter-760",
      "dateUpdateChapter": "2023-12-06 07:41:00"
    },
    {
      "urlChapter": "chapter-759",
      "dateUpdateChapter": "2023-12-06 07:40:56"
    },
    {
      "urlChapter": "chapter-758",
      "dateUpdateChapter": "2023-12-06 07:40:54"
    },
    {
      "urlChapter": "chapter-757",
      "dateUpdateChapter": "2023-12-06 07:40:52"
    },
    {
      "urlChapter": "chapter-756",
      "dateUpdateChapter": "2023-12-06 07:40:50"
    },
    {
      "urlChapter": "chapter-755",
      "dateUpdateChapter": "2023-12-06 07:40:49"
    },
    {
      "urlChapter": "chapter-754",
      "dateUpdateChapter": "2023-12-06 07:40:47"
    },
    {
      "urlChapter": "chapter-753",
      "dateUpdateChapter": "2023-12-06 07:40:45"
    },
    {
      "urlChapter": "chapter-752",
      "dateUpdateChapter": "2023-12-06 07:40:42"
    },
    {
      "urlChapter": "chapter-751",
      "dateUpdateChapter": "2023-12-06 07:40:40"
    },
    {
      "urlChapter": "chapter-750",
      "dateUpdateChapter": "2023-12-06 07:40:38"
    },
    {
      "urlChapter": "chapter-749",
      "dateUpdateChapter": "2023-12-06 07:40:36"
    },
    {
      "urlChapter": "chapter-748",
      "dateUpdateChapter": "2023-12-06 07:40:33"
    },
    {
      "urlChapter": "chapter-747",
      "dateUpdateChapter": "2023-12-06 07:40:31"
    },
    {
      "urlChapter": "chapter-746",
      "dateUpdateChapter": "2023-12-06 07:40:28"
    },
    {
      "urlChapter": "chapter-745",
      "dateUpdateChapter": "2023-12-06 07:40:27"
    },
    {
      "urlChapter": "chapter-744",
      "dateUpdateChapter": "2023-12-06 07:40:24"
    },
    {
      "urlChapter": "chapter-743",
      "dateUpdateChapter": "2023-12-06 07:40:22"
    },
    {
      "urlChapter": "chapter-742",
      "dateUpdateChapter": "2023-12-06 07:40:19"
    },
    {
      "urlChapter": "chapter-741",
      "dateUpdateChapter": "2023-12-06 07:40:17"
    },
    {
      "urlChapter": "chapter-740",
      "dateUpdateChapter": "2023-12-06 07:40:15"
    },
    {
      "urlChapter": "chapter-739",
      "dateUpdateChapter": "2023-12-06 07:40:13"
    },
    {
      "urlChapter": "chapter-738",
      "dateUpdateChapter": "2023-12-06 07:40:12"
    },
    {
      "urlChapter": "chapter-737",
      "dateUpdateChapter": "2023-12-06 07:40:10"
    },
    {
      "urlChapter": "chapter-736",
      "dateUpdateChapter": "2023-12-06 07:40:08"
    },
    {
      "urlChapter": "chapter-735",
      "dateUpdateChapter": "2023-12-06 07:40:06"
    },
    {
      "urlChapter": "chapter-734",
      "dateUpdateChapter": "2023-12-06 07:40:04"
    },
    {
      "urlChapter": "chapter-733",
      "dateUpdateChapter": "2023-12-06 07:40:02"
    },
    {
      "urlChapter": "chapter-732",
      "dateUpdateChapter": "2023-12-06 07:40:00"
    },
    {
      "urlChapter": "chapter-731",
      "dateUpdateChapter": "2023-12-06 07:39:58"
    },
    {
      "urlChapter": "chapter-730",
      "dateUpdateChapter": "2023-12-06 07:39:57"
    },
    {
      "urlChapter": "chapter-729",
      "dateUpdateChapter": "2023-12-06 07:39:55"
    },
    {
      "urlChapter": "chapter-728",
      "dateUpdateChapter": "2023-12-06 07:39:52"
    },
    {
      "urlChapter": "chapter-727",
      "dateUpdateChapter": "2023-12-06 07:39:51"
    },
    {
      "urlChapter": "chapter-726",
      "dateUpdateChapter": "2023-12-06 07:39:49"
    },
    {
      "urlChapter": "chapter-725",
      "dateUpdateChapter": "2023-12-06 07:39:46"
    },
    {
      "urlChapter": "chapter-724",
      "dateUpdateChapter": "2023-12-06 07:39:45"
    },
    {
      "urlChapter": "chapter-723",
      "dateUpdateChapter": "2023-12-06 07:39:43"
    },
    {
      "urlChapter": "chapter-722",
      "dateUpdateChapter": "2023-12-06 07:39:41"
    },
    {
      "urlChapter": "chapter-721",
      "dateUpdateChapter": "2023-12-06 07:39:39"
    },
    {
      "urlChapter": "chapter-720",
      "dateUpdateChapter": "2023-12-06 07:39:37"
    },
    {
      "urlChapter": "chapter-719",
      "dateUpdateChapter": "2023-12-06 07:39:35"
    },
    {
      "urlChapter": "chapter-718",
      "dateUpdateChapter": "2023-12-06 07:39:32"
    },
    {
      "urlChapter": "chapter-717",
      "dateUpdateChapter": "2023-12-06 07:39:30"
    },
    {
      "urlChapter": "chapter-716",
      "dateUpdateChapter": "2023-12-06 07:39:28"
    },
    {
      "urlChapter": "chapter-715",
      "dateUpdateChapter": "2023-12-06 07:39:27"
    },
    {
      "urlChapter": "chapter-714",
      "dateUpdateChapter": "2023-12-06 07:39:25"
    },
    {
      "urlChapter": "chapter-713",
      "dateUpdateChapter": "2023-12-06 07:39:22"
    },
    {
      "urlChapter": "chapter-712",
      "dateUpdateChapter": "2023-12-06 07:39:21"
    },
    {
      "urlChapter": "chapter-711",
      "dateUpdateChapter": "2023-12-06 07:39:19"
    },
    {
      "urlChapter": "chapter-710",
      "dateUpdateChapter": "2023-12-06 07:39:17"
    },
    {
      "urlChapter": "chapter-709",
      "dateUpdateChapter": "2023-12-06 07:39:15"
    },
    {
      "urlChapter": "chapter-708",
      "dateUpdateChapter": "2023-12-06 07:39:13"
    },
    {
      "urlChapter": "chapter-707",
      "dateUpdateChapter": "2023-12-06 07:39:11"
    },
    {
      "urlChapter": "chapter-706",
      "dateUpdateChapter": "2023-12-06 07:39:10"
    },
    {
      "urlChapter": "chapter-705",
      "dateUpdateChapter": "2023-12-06 07:39:08"
    },
    {
      "urlChapter": "chapter-704",
      "dateUpdateChapter": "2023-12-06 07:39:07"
    },
    {
      "urlChapter": "chapter-703",
      "dateUpdateChapter": "2023-12-06 07:39:06"
    },
    {
      "urlChapter": "chapter-702",
      "dateUpdateChapter": "2023-12-06 07:39:05"
    },
    {
      "urlChapter": "chapter-701",
      "dateUpdateChapter": "2023-12-06 07:39:03"
    },
    {
      "urlChapter": "chapter-700",
      "dateUpdateChapter": "2023-12-06 07:39:01"
    },
    {
      "urlChapter": "chapter-699",
      "dateUpdateChapter": "2023-12-06 07:38:59"
    },
    {
      "urlChapter": "chapter-698",
      "dateUpdateChapter": "2023-12-06 07:38:56"
    },
    {
      "urlChapter": "chapter-697",
      "dateUpdateChapter": "2023-12-06 07:38:54"
    },
    {
      "urlChapter": "chapter-696",
      "dateUpdateChapter": "2023-12-06 07:38:52"
    },
    {
      "urlChapter": "chapter-695",
      "dateUpdateChapter": "2023-12-06 07:38:48"
    },
    {
      "urlChapter": "chapter-694",
      "dateUpdateChapter": "2023-12-06 07:38:46"
    },
    {
      "urlChapter": "chapter-693",
      "dateUpdateChapter": "2023-12-06 07:38:44"
    },
    {
      "urlChapter": "chapter-692",
      "dateUpdateChapter": "2023-12-06 07:38:42"
    },
    {
      "urlChapter": "chapter-691",
      "dateUpdateChapter": "2023-12-06 07:38:40"
    },
    {
      "urlChapter": "chapter-690",
      "dateUpdateChapter": "2023-12-06 07:38:38"
    },
    {
      "urlChapter": "chapter-689",
      "dateUpdateChapter": "2023-12-06 07:38:37"
    },
    {
      "urlChapter": "chapter-688",
      "dateUpdateChapter": "2023-12-06 07:38:35"
    },
    {
      "urlChapter": "chapter-687",
      "dateUpdateChapter": "2023-12-06 07:38:34"
    },
    {
      "urlChapter": "chapter-686",
      "dateUpdateChapter": "2023-12-06 07:38:33"
    },
    {
      "urlChapter": "chapter-685",
      "dateUpdateChapter": "2023-12-06 07:38:31"
    },
    {
      "urlChapter": "chapter-684",
      "dateUpdateChapter": "2023-12-06 07:38:29"
    },
    {
      "urlChapter": "chapter-683",
      "dateUpdateChapter": "2023-12-06 07:38:28"
    },
    {
      "urlChapter": "chapter-682",
      "dateUpdateChapter": "2023-12-06 07:38:27"
    },
    {
      "urlChapter": "chapter-681",
      "dateUpdateChapter": "2023-12-06 07:38:25"
    },
    {
      "urlChapter": "chapter-680",
      "dateUpdateChapter": "2023-12-06 07:38:24"
    },
    {
      "urlChapter": "chapter-679",
      "dateUpdateChapter": "2023-12-06 07:38:22"
    },
    {
      "urlChapter": "chapter-678",
      "dateUpdateChapter": "2023-12-06 07:38:21"
    },
    {
      "urlChapter": "chapter-677",
      "dateUpdateChapter": "2023-12-06 07:38:19"
    },
    {
      "urlChapter": "chapter-676",
      "dateUpdateChapter": "2023-12-06 07:38:18"
    },
    {
      "urlChapter": "chapter-675",
      "dateUpdateChapter": "2023-12-06 07:38:16"
    },
    {
      "urlChapter": "chapter-674",
      "dateUpdateChapter": "2023-12-06 07:38:14"
    },
    {
      "urlChapter": "chapter-673",
      "dateUpdateChapter": "2023-12-06 07:38:13"
    },
    {
      "urlChapter": "chapter-672",
      "dateUpdateChapter": "2023-12-06 07:38:12"
    },
    {
      "urlChapter": "chapter-671",
      "dateUpdateChapter": "2023-12-06 07:38:10"
    },
    {
      "urlChapter": "chapter-670",
      "dateUpdateChapter": "2023-12-06 07:38:09"
    },
    {
      "urlChapter": "chapter-669",
      "dateUpdateChapter": "2023-12-06 07:38:07"
    },
    {
      "urlChapter": "chapter-668",
      "dateUpdateChapter": "2023-12-06 07:38:06"
    },
    {
      "urlChapter": "chapter-667",
      "dateUpdateChapter": "2023-12-06 07:38:04"
    },
    {
      "urlChapter": "chapter-666",
      "dateUpdateChapter": "2023-12-06 07:38:03"
    },
    {
      "urlChapter": "chapter-665",
      "dateUpdateChapter": "2023-12-06 07:38:01"
    },
    {
      "urlChapter": "chapter-664",
      "dateUpdateChapter": "2023-12-06 07:37:59"
    },
    {
      "urlChapter": "chapter-663",
      "dateUpdateChapter": "2023-12-06 07:37:56"
    },
    {
      "urlChapter": "chapter-662",
      "dateUpdateChapter": "2023-12-06 07:37:54"
    },
    {
      "urlChapter": "chapter-661",
      "dateUpdateChapter": "2023-12-06 07:37:51"
    },
    {
      "urlChapter": "chapter-660",
      "dateUpdateChapter": "2023-12-06 07:37:49"
    },
    {
      "urlChapter": "chapter-659",
      "dateUpdateChapter": "2023-12-06 07:37:47"
    },
    {
      "urlChapter": "chapter-658",
      "dateUpdateChapter": "2023-12-06 07:37:45"
    },
    {
      "urlChapter": "chapter-657",
      "dateUpdateChapter": "2023-12-06 07:37:43"
    },
    {
      "urlChapter": "chapter-656",
      "dateUpdateChapter": "2023-12-06 07:37:42"
    },
    {
      "urlChapter": "chapter-655",
      "dateUpdateChapter": "2023-12-06 07:37:40"
    },
    {
      "urlChapter": "chapter-654",
      "dateUpdateChapter": "2023-12-06 07:37:38"
    },
    {
      "urlChapter": "chapter-653",
      "dateUpdateChapter": "2023-12-06 07:37:36"
    },
    {
      "urlChapter": "chapter-652",
      "dateUpdateChapter": "2023-12-06 07:37:35"
    },
    {
      "urlChapter": "chapter-651",
      "dateUpdateChapter": "2023-12-06 07:37:33"
    },
    {
      "urlChapter": "chapter-650",
      "dateUpdateChapter": "2023-12-06 07:37:31"
    },
    {
      "urlChapter": "chapter-649",
      "dateUpdateChapter": "2023-12-06 07:37:29"
    },
    {
      "urlChapter": "chapter-648",
      "dateUpdateChapter": "2023-12-06 07:37:27"
    },
    {
      "urlChapter": "chapter-647",
      "dateUpdateChapter": "2023-12-06 07:37:26"
    },
    {
      "urlChapter": "chapter-646",
      "dateUpdateChapter": "2023-12-06 07:37:24"
    },
    {
      "urlChapter": "chapter-645",
      "dateUpdateChapter": "2023-12-06 07:37:22"
    },
    {
      "urlChapter": "chapter-644",
      "dateUpdateChapter": "2023-12-06 07:37:21"
    },
    {
      "urlChapter": "chapter-643",
      "dateUpdateChapter": "2023-12-06 07:37:19"
    },
    {
      "urlChapter": "chapter-642",
      "dateUpdateChapter": "2023-12-06 07:37:18"
    },
    {
      "urlChapter": "chapter-641",
      "dateUpdateChapter": "2023-12-06 07:37:16"
    },
    {
      "urlChapter": "chapter-640",
      "dateUpdateChapter": "2023-12-06 07:37:14"
    },
    {
      "urlChapter": "chapter-639",
      "dateUpdateChapter": "2023-12-06 07:37:12"
    },
    {
      "urlChapter": "chapter-638",
      "dateUpdateChapter": "2023-12-06 07:37:11"
    },
    {
      "urlChapter": "chapter-637",
      "dateUpdateChapter": "2023-12-06 07:37:10"
    },
    {
      "urlChapter": "chapter-636",
      "dateUpdateChapter": "2023-12-06 07:37:08"
    },
    {
      "urlChapter": "chapter-635",
      "dateUpdateChapter": "2023-12-06 07:37:06"
    },
    {
      "urlChapter": "chapter-634",
      "dateUpdateChapter": "2023-12-06 07:37:04"
    },
    {
      "urlChapter": "chapter-633",
      "dateUpdateChapter": "2023-12-06 07:37:02"
    },
    {
      "urlChapter": "chapter-632",
      "dateUpdateChapter": "2023-12-06 07:37:01"
    },
    {
      "urlChapter": "chapter-631",
      "dateUpdateChapter": "2023-12-06 07:37:00"
    },
    {
      "urlChapter": "chapter-630",
      "dateUpdateChapter": "2023-12-06 07:36:59"
    },
    {
      "urlChapter": "chapter-629",
      "dateUpdateChapter": "2023-12-06 07:36:57"
    },
    {
      "urlChapter": "chapter-628",
      "dateUpdateChapter": "2023-12-06 07:36:56"
    },
    {
      "urlChapter": "chapter-627",
      "dateUpdateChapter": "2023-12-06 07:36:55"
    },
    {
      "urlChapter": "chapter-626",
      "dateUpdateChapter": "2023-12-06 07:36:53"
    },
    {
      "urlChapter": "chapter-625",
      "dateUpdateChapter": "2023-12-06 07:36:51"
    },
    {
      "urlChapter": "chapter-624",
      "dateUpdateChapter": "2023-12-06 07:36:50"
    },
    {
      "urlChapter": "chapter-623",
      "dateUpdateChapter": "2023-12-06 07:36:48"
    },
    {
      "urlChapter": "chapter-622",
      "dateUpdateChapter": "2023-12-06 07:36:47"
    },
    {
      "urlChapter": "chapter-621",
      "dateUpdateChapter": "2023-12-06 07:36:45"
    },
    {
      "urlChapter": "chapter-620",
      "dateUpdateChapter": "2023-12-06 07:36:44"
    },
    {
      "urlChapter": "chapter-619",
      "dateUpdateChapter": "2023-12-06 07:36:42"
    },
    {
      "urlChapter": "chapter-618",
      "dateUpdateChapter": "2023-12-06 07:36:40"
    },
    {
      "urlChapter": "chapter-617",
      "dateUpdateChapter": "2023-12-06 07:36:39"
    },
    {
      "urlChapter": "chapter-616",
      "dateUpdateChapter": "2023-12-06 07:36:37"
    },
    {
      "urlChapter": "chapter-615",
      "dateUpdateChapter": "2023-12-06 07:36:36"
    },
    {
      "urlChapter": "chapter-614",
      "dateUpdateChapter": "2023-12-06 07:36:34"
    },
    {
      "urlChapter": "chapter-613",
      "dateUpdateChapter": "2023-12-06 07:36:32"
    },
    {
      "urlChapter": "chapter-612",
      "dateUpdateChapter": "2023-12-06 07:36:30"
    },
    {
      "urlChapter": "chapter-611",
      "dateUpdateChapter": "2023-12-06 07:36:28"
    },
    {
      "urlChapter": "chapter-610",
      "dateUpdateChapter": "2023-12-06 07:36:27"
    },
    {
      "urlChapter": "chapter-609",
      "dateUpdateChapter": "2023-12-06 07:36:25"
    },
    {
      "urlChapter": "chapter-608",
      "dateUpdateChapter": "2023-12-06 07:36:23"
    },
    {
      "urlChapter": "chapter-607",
      "dateUpdateChapter": "2023-12-06 07:36:22"
    },
    {
      "urlChapter": "chapter-606",
      "dateUpdateChapter": "2023-12-06 07:36:20"
    },
    {
      "urlChapter": "chapter-605",
      "dateUpdateChapter": "2023-12-06 07:36:18"
    },
    {
      "urlChapter": "chapter-604",
      "dateUpdateChapter": "2023-12-06 07:36:16"
    },
    {
      "urlChapter": "chapter-603",
      "dateUpdateChapter": "2023-12-06 07:36:15"
    },
    {
      "urlChapter": "chapter-602",
      "dateUpdateChapter": "2023-12-06 07:36:13"
    },
    {
      "urlChapter": "chapter-601",
      "dateUpdateChapter": "2023-12-06 07:36:11"
    },
    {
      "urlChapter": "chapter-600",
      "dateUpdateChapter": "2023-12-06 07:36:09"
    },
    {
      "urlChapter": "chapter-599",
      "dateUpdateChapter": "2023-12-06 07:36:08"
    },
    {
      "urlChapter": "chapter-598",
      "dateUpdateChapter": "2023-12-06 07:36:06"
    },
    {
      "urlChapter": "chapter-597",
      "dateUpdateChapter": "2023-12-06 07:36:04"
    },
    {
      "urlChapter": "chapter-596",
      "dateUpdateChapter": "2023-12-06 07:36:02"
    },
    {
      "urlChapter": "chapter-595",
      "dateUpdateChapter": "2023-12-06 07:36:00"
    },
    {
      "urlChapter": "chapter-594",
      "dateUpdateChapter": "2023-12-06 07:35:58"
    },
    {
      "urlChapter": "chapter-593",
      "dateUpdateChapter": "2023-12-06 07:35:57"
    },
    {
      "urlChapter": "chapter-592",
      "dateUpdateChapter": "2023-12-06 07:35:54"
    },
    {
      "urlChapter": "chapter-591",
      "dateUpdateChapter": "2023-12-06 07:35:52"
    },
    {
      "urlChapter": "chapter-590",
      "dateUpdateChapter": "2023-12-06 07:35:49"
    },
    {
      "urlChapter": "chapter-589",
      "dateUpdateChapter": "2023-12-06 07:35:48"
    },
    {
      "urlChapter": "chapter-588",
      "dateUpdateChapter": "2023-12-06 07:35:46"
    },
    {
      "urlChapter": "chapter-587",
      "dateUpdateChapter": "2023-12-06 07:35:45"
    },
    {
      "urlChapter": "chapter-586",
      "dateUpdateChapter": "2023-12-06 07:35:43"
    },
    {
      "urlChapter": "chapter-585",
      "dateUpdateChapter": "2023-12-06 07:35:40"
    },
    {
      "urlChapter": "chapter-584",
      "dateUpdateChapter": "2023-12-06 07:35:39"
    },
    {
      "urlChapter": "chapter-583",
      "dateUpdateChapter": "2023-12-06 07:35:37"
    },
    {
      "urlChapter": "chapter-582",
      "dateUpdateChapter": "2023-12-06 07:35:35"
    },
    {
      "urlChapter": "chapter-581",
      "dateUpdateChapter": "2023-12-06 07:35:33"
    },
    {
      "urlChapter": "chapter-580",
      "dateUpdateChapter": "2023-12-06 07:35:31"
    },
    {
      "urlChapter": "chapter-579",
      "dateUpdateChapter": "2023-12-06 07:35:30"
    },
    {
      "urlChapter": "chapter-578",
      "dateUpdateChapter": "2023-12-06 07:35:27"
    },
    {
      "urlChapter": "chapter-577",
      "dateUpdateChapter": "2023-12-06 07:35:25"
    },
    {
      "urlChapter": "chapter-576",
      "dateUpdateChapter": "2023-12-06 07:35:23"
    },
    {
      "urlChapter": "chapter-575",
      "dateUpdateChapter": "2023-12-06 07:35:21"
    },
    {
      "urlChapter": "chapter-574",
      "dateUpdateChapter": "2023-12-06 07:35:19"
    },
    {
      "urlChapter": "chapter-573",
      "dateUpdateChapter": "2023-12-06 07:35:18"
    },
    {
      "urlChapter": "chapter-572",
      "dateUpdateChapter": "2023-12-06 07:35:15"
    },
    {
      "urlChapter": "chapter-571",
      "dateUpdateChapter": "2023-12-06 07:35:13"
    },
    {
      "urlChapter": "chapter-570",
      "dateUpdateChapter": "2023-12-06 07:35:12"
    },
    {
      "urlChapter": "chapter-569",
      "dateUpdateChapter": "2023-12-06 07:35:10"
    },
    {
      "urlChapter": "chapter-568",
      "dateUpdateChapter": "2023-12-06 07:35:08"
    },
    {
      "urlChapter": "chapter-567",
      "dateUpdateChapter": "2023-12-06 07:35:06"
    },
    {
      "urlChapter": "chapter-566",
      "dateUpdateChapter": "2023-12-06 07:35:05"
    },
    {
      "urlChapter": "chapter-565",
      "dateUpdateChapter": "2023-12-06 07:35:03"
    },
    {
      "urlChapter": "chapter-564",
      "dateUpdateChapter": "2023-12-06 07:35:01"
    },
    {
      "urlChapter": "chapter-563",
      "dateUpdateChapter": "2023-12-06 07:35:00"
    },
    {
      "urlChapter": "chapter-562",
      "dateUpdateChapter": "2023-12-06 07:34:58"
    },
    {
      "urlChapter": "chapter-561",
      "dateUpdateChapter": "2023-12-06 07:34:56"
    },
    {
      "urlChapter": "chapter-560",
      "dateUpdateChapter": "2023-12-06 07:34:54"
    },
    {
      "urlChapter": "chapter-559",
      "dateUpdateChapter": "2023-12-06 07:34:52"
    },
    {
      "urlChapter": "chapter-558",
      "dateUpdateChapter": "2023-12-06 07:34:50"
    },
    {
      "urlChapter": "chapter-557",
      "dateUpdateChapter": "2023-12-06 07:34:48"
    },
    {
      "urlChapter": "chapter-556",
      "dateUpdateChapter": "2023-12-06 07:34:46"
    },
    {
      "urlChapter": "chapter-555",
      "dateUpdateChapter": "2023-12-06 07:34:44"
    },
    {
      "urlChapter": "chapter-554",
      "dateUpdateChapter": "2023-12-06 07:34:42"
    },
    {
      "urlChapter": "chapter-553",
      "dateUpdateChapter": "2023-12-06 07:34:40"
    },
    {
      "urlChapter": "chapter-552",
      "dateUpdateChapter": "2023-12-06 07:34:39"
    },
    {
      "urlChapter": "chapter-551",
      "dateUpdateChapter": "2023-12-06 07:34:37"
    },
    {
      "urlChapter": "chapter-550",
      "dateUpdateChapter": "2023-12-06 07:34:35"
    },
    {
      "urlChapter": "chapter-549",
      "dateUpdateChapter": "2023-12-06 07:34:33"
    },
    {
      "urlChapter": "chapter-548",
      "dateUpdateChapter": "2023-12-06 07:34:32"
    },
    {
      "urlChapter": "chapter-547",
      "dateUpdateChapter": "2023-12-06 07:34:30"
    },
    {
      "urlChapter": "chapter-546",
      "dateUpdateChapter": "2023-12-06 07:34:28"
    },
    {
      "urlChapter": "chapter-545",
      "dateUpdateChapter": "2023-12-06 07:34:26"
    },
    {
      "urlChapter": "chapter-544",
      "dateUpdateChapter": "2023-12-06 07:34:24"
    },
    {
      "urlChapter": "chapter-543",
      "dateUpdateChapter": "2023-12-06 07:34:22"
    },
    {
      "urlChapter": "chapter-542",
      "dateUpdateChapter": "2023-12-06 07:34:21"
    },
    {
      "urlChapter": "chapter-541",
      "dateUpdateChapter": "2023-12-06 07:34:19"
    },
    {
      "urlChapter": "chapter-540",
      "dateUpdateChapter": "2023-12-06 07:34:17"
    },
    {
      "urlChapter": "chapter-539",
      "dateUpdateChapter": "2023-12-06 07:34:16"
    },
    {
      "urlChapter": "chapter-538",
      "dateUpdateChapter": "2023-12-06 07:34:14"
    },
    {
      "urlChapter": "chapter-537",
      "dateUpdateChapter": "2023-12-06 07:34:13"
    },
    {
      "urlChapter": "chapter-536",
      "dateUpdateChapter": "2023-12-06 07:34:11"
    },
    {
      "urlChapter": "chapter-535",
      "dateUpdateChapter": "2023-12-06 07:34:09"
    },
    {
      "urlChapter": "chapter-534",
      "dateUpdateChapter": "2023-12-06 07:34:07"
    },
    {
      "urlChapter": "chapter-533",
      "dateUpdateChapter": "2023-12-06 07:34:06"
    },
    {
      "urlChapter": "chapter-532",
      "dateUpdateChapter": "2023-12-06 07:34:04"
    },
    {
      "urlChapter": "chapter-531",
      "dateUpdateChapter": "2023-12-06 07:34:02"
    },
    {
      "urlChapter": "chapter-530",
      "dateUpdateChapter": "2023-12-06 07:34:00"
    },
    {
      "urlChapter": "chapter-529",
      "dateUpdateChapter": "2023-12-06 07:33:58"
    },
    {
      "urlChapter": "chapter-528",
      "dateUpdateChapter": "2023-12-06 07:33:56"
    },
    {
      "urlChapter": "chapter-527",
      "dateUpdateChapter": "2023-12-06 07:33:48"
    },
    {
      "urlChapter": "chapter-526",
      "dateUpdateChapter": "2023-12-06 07:33:47"
    },
    {
      "urlChapter": "chapter-525",
      "dateUpdateChapter": "2023-12-06 07:33:45"
    },
    {
      "urlChapter": "chapter-524",
      "dateUpdateChapter": "2023-12-06 07:33:43"
    },
    {
      "urlChapter": "chapter-523",
      "dateUpdateChapter": "2023-12-06 07:33:42"
    },
    {
      "urlChapter": "chapter-522",
      "dateUpdateChapter": "2023-12-06 07:33:39"
    },
    {
      "urlChapter": "chapter-521",
      "dateUpdateChapter": "2023-12-06 07:33:37"
    },
    {
      "urlChapter": "chapter-520",
      "dateUpdateChapter": "2023-12-06 07:33:35"
    },
    {
      "urlChapter": "chapter-519",
      "dateUpdateChapter": "2023-12-06 07:33:34"
    },
    {
      "urlChapter": "chapter-518",
      "dateUpdateChapter": "2023-12-06 07:33:32"
    },
    {
      "urlChapter": "chapter-517",
      "dateUpdateChapter": "2023-12-06 07:33:30"
    },
    {
      "urlChapter": "chapter-516",
      "dateUpdateChapter": "2023-12-06 07:33:28"
    },
    {
      "urlChapter": "chapter-515",
      "dateUpdateChapter": "2023-12-06 07:33:26"
    },
    {
      "urlChapter": "chapter-514",
      "dateUpdateChapter": "2023-12-06 07:33:24"
    },
    {
      "urlChapter": "chapter-513",
      "dateUpdateChapter": "2023-12-06 07:33:22"
    },
    {
      "urlChapter": "chapter-512",
      "dateUpdateChapter": "2023-12-06 07:33:20"
    },
    {
      "urlChapter": "chapter-511",
      "dateUpdateChapter": "2023-12-06 07:33:18"
    },
    {
      "urlChapter": "chapter-510",
      "dateUpdateChapter": "2023-12-06 07:33:16"
    },
    {
      "urlChapter": "chapter-509",
      "dateUpdateChapter": "2023-12-06 07:33:14"
    },
    {
      "urlChapter": "chapter-508",
      "dateUpdateChapter": "2023-12-06 07:33:12"
    },
    {
      "urlChapter": "chapter-507",
      "dateUpdateChapter": "2023-12-06 07:33:08"
    },
    {
      "urlChapter": "chapter-506",
      "dateUpdateChapter": "2023-12-06 07:33:06"
    },
    {
      "urlChapter": "chapter-505",
      "dateUpdateChapter": "2023-12-06 07:33:05"
    },
    {
      "urlChapter": "chapter-504",
      "dateUpdateChapter": "2023-12-06 07:33:03"
    },
    {
      "urlChapter": "chapter-503",
      "dateUpdateChapter": "2023-12-06 07:33:01"
    },
    {
      "urlChapter": "chapter-502",
      "dateUpdateChapter": "2023-12-06 07:33:00"
    },
    {
      "urlChapter": "chapter-501",
      "dateUpdateChapter": "2023-12-06 07:32:59"
    },
    {
      "urlChapter": "chapter-500",
      "dateUpdateChapter": "2023-12-06 07:32:57"
    },
    {
      "urlChapter": "chapter-499",
      "dateUpdateChapter": "2023-12-06 07:32:55"
    },
    {
      "urlChapter": "chapter-498",
      "dateUpdateChapter": "2023-12-06 07:32:53"
    },
    {
      "urlChapter": "chapter-497",
      "dateUpdateChapter": "2023-12-06 07:32:52"
    },
    {
      "urlChapter": "chapter-496",
      "dateUpdateChapter": "2023-12-06 07:32:50"
    },
    {
      "urlChapter": "chapter-495",
      "dateUpdateChapter": "2023-12-06 07:32:48"
    },
    {
      "urlChapter": "chapter-494",
      "dateUpdateChapter": "2023-12-06 07:32:46"
    },
    {
      "urlChapter": "chapter-493",
      "dateUpdateChapter": "2023-12-06 07:32:44"
    },
    {
      "urlChapter": "chapter-492",
      "dateUpdateChapter": "2023-12-06 07:32:43"
    },
    {
      "urlChapter": "chapter-491",
      "dateUpdateChapter": "2023-12-06 07:32:41"
    },
    {
      "urlChapter": "chapter-490",
      "dateUpdateChapter": "2023-12-06 07:32:39"
    },
    {
      "urlChapter": "chapter-489",
      "dateUpdateChapter": "2023-12-06 07:32:37"
    },
    {
      "urlChapter": "chapter-488",
      "dateUpdateChapter": "2023-12-06 07:32:35"
    },
    {
      "urlChapter": "chapter-487",
      "dateUpdateChapter": "2023-12-06 07:32:34"
    },
    {
      "urlChapter": "chapter-486",
      "dateUpdateChapter": "2023-12-06 07:32:32"
    },
    {
      "urlChapter": "chapter-485",
      "dateUpdateChapter": "2023-12-06 07:32:31"
    },
    {
      "urlChapter": "chapter-484",
      "dateUpdateChapter": "2023-12-06 07:32:29"
    },
    {
      "urlChapter": "chapter-483",
      "dateUpdateChapter": "2023-12-06 07:32:27"
    },
    {
      "urlChapter": "chapter-482",
      "dateUpdateChapter": "2023-12-06 07:32:25"
    },
    {
      "urlChapter": "chapter-481",
      "dateUpdateChapter": "2023-12-06 07:32:23"
    },
    {
      "urlChapter": "chapter-480",
      "dateUpdateChapter": "2023-12-06 07:32:22"
    },
    {
      "urlChapter": "chapter-479",
      "dateUpdateChapter": "2023-12-06 07:32:20"
    },
    {
      "urlChapter": "chapter-478",
      "dateUpdateChapter": "2023-12-06 07:32:18"
    },
    {
      "urlChapter": "chapter-477",
      "dateUpdateChapter": "2023-12-06 07:32:16"
    },
    {
      "urlChapter": "chapter-476",
      "dateUpdateChapter": "2023-12-06 07:32:14"
    },
    {
      "urlChapter": "chapter-475",
      "dateUpdateChapter": "2023-12-06 07:32:12"
    },
    {
      "urlChapter": "chapter-474",
      "dateUpdateChapter": "2023-12-06 07:32:10"
    },
    {
      "urlChapter": "chapter-473",
      "dateUpdateChapter": "2023-12-06 07:32:09"
    },
    {
      "urlChapter": "chapter-472",
      "dateUpdateChapter": "2023-12-06 07:32:07"
    },
    {
      "urlChapter": "chapter-471",
      "dateUpdateChapter": "2023-12-06 07:32:06"
    },
    {
      "urlChapter": "chapter-470",
      "dateUpdateChapter": "2023-12-06 07:32:05"
    },
    {
      "urlChapter": "chapter-469",
      "dateUpdateChapter": "2023-12-06 07:32:03"
    },
    {
      "urlChapter": "chapter-468",
      "dateUpdateChapter": "2023-12-06 07:32:01"
    },
    {
      "urlChapter": "chapter-467",
      "dateUpdateChapter": "2023-12-06 07:31:59"
    },
    {
      "urlChapter": "chapter-466",
      "dateUpdateChapter": "2023-12-06 07:31:56"
    },
    {
      "urlChapter": "chapter-465",
      "dateUpdateChapter": "2023-12-06 07:31:55"
    },
    {
      "urlChapter": "chapter-464",
      "dateUpdateChapter": "2023-12-06 07:31:53"
    },
    {
      "urlChapter": "chapter-463",
      "dateUpdateChapter": "2023-12-06 07:31:51"
    },
    {
      "urlChapter": "chapter-462",
      "dateUpdateChapter": "2023-12-06 07:31:49"
    },
    {
      "urlChapter": "chapter-461",
      "dateUpdateChapter": "2023-12-06 07:31:46"
    },
    {
      "urlChapter": "chapter-460",
      "dateUpdateChapter": "2023-12-06 07:31:45"
    },
    {
      "urlChapter": "chapter-459",
      "dateUpdateChapter": "2023-12-06 07:31:43"
    },
    {
      "urlChapter": "chapter-458",
      "dateUpdateChapter": "2023-12-06 07:31:41"
    },
    {
      "urlChapter": "chapter-457",
      "dateUpdateChapter": "2023-12-06 07:31:39"
    },
    {
      "urlChapter": "chapter-456",
      "dateUpdateChapter": "2023-12-06 07:31:37"
    },
    {
      "urlChapter": "chapter-455",
      "dateUpdateChapter": "2023-12-06 07:31:35"
    },
    {
      "urlChapter": "chapter-454",
      "dateUpdateChapter": "2023-12-06 07:31:33"
    },
    {
      "urlChapter": "chapter-453",
      "dateUpdateChapter": "2023-12-06 07:31:32"
    },
    {
      "urlChapter": "chapter-452",
      "dateUpdateChapter": "2023-12-06 07:31:30"
    },
    {
      "urlChapter": "chapter-451",
      "dateUpdateChapter": "2023-12-06 07:31:28"
    },
    {
      "urlChapter": "chapter-450",
      "dateUpdateChapter": "2023-12-06 07:31:27"
    },
    {
      "urlChapter": "chapter-449",
      "dateUpdateChapter": "2023-12-06 07:31:25"
    },
    {
      "urlChapter": "chapter-448",
      "dateUpdateChapter": "2023-12-06 07:31:23"
    },
    {
      "urlChapter": "chapter-447",
      "dateUpdateChapter": "2023-12-06 07:31:22"
    },
    {
      "urlChapter": "chapter-446",
      "dateUpdateChapter": "2023-12-06 07:31:19"
    },
    {
      "urlChapter": "chapter-445",
      "dateUpdateChapter": "2023-12-06 07:31:17"
    },
    {
      "urlChapter": "chapter-444",
      "dateUpdateChapter": "2023-12-06 07:31:15"
    },
    {
      "urlChapter": "chapter-443",
      "dateUpdateChapter": "2023-12-06 07:31:14"
    },
    {
      "urlChapter": "chapter-442",
      "dateUpdateChapter": "2023-12-06 07:31:12"
    },
    {
      "urlChapter": "chapter-441",
      "dateUpdateChapter": "2023-12-06 07:31:10"
    },
    {
      "urlChapter": "chapter-440",
      "dateUpdateChapter": "2023-12-06 07:31:08"
    },
    {
      "urlChapter": "chapter-439",
      "dateUpdateChapter": "2023-12-06 07:31:06"
    },
    {
      "urlChapter": "chapter-438",
      "dateUpdateChapter": "2023-12-06 07:31:05"
    },
    {
      "urlChapter": "chapter-437",
      "dateUpdateChapter": "2023-12-06 07:31:03"
    },
    {
      "urlChapter": "chapter-436",
      "dateUpdateChapter": "2023-12-06 07:31:01"
    },
    {
      "urlChapter": "chapter-435",
      "dateUpdateChapter": "2023-12-06 07:30:59"
    },
    {
      "urlChapter": "chapter-434",
      "dateUpdateChapter": "2023-12-06 07:30:58"
    },
    {
      "urlChapter": "chapter-433",
      "dateUpdateChapter": "2023-12-06 07:30:56"
    },
    {
      "urlChapter": "chapter-432",
      "dateUpdateChapter": "2023-12-06 07:30:55"
    },
    {
      "urlChapter": "chapter-431",
      "dateUpdateChapter": "2023-12-06 07:30:53"
    },
    {
      "urlChapter": "chapter-430",
      "dateUpdateChapter": "2023-12-06 07:30:51"
    },
    {
      "urlChapter": "chapter-429",
      "dateUpdateChapter": "2023-12-06 07:30:49"
    },
    {
      "urlChapter": "chapter-428",
      "dateUpdateChapter": "2023-12-06 07:30:48"
    },
    {
      "urlChapter": "chapter-427",
      "dateUpdateChapter": "2023-12-06 07:30:45"
    },
    {
      "urlChapter": "chapter-426",
      "dateUpdateChapter": "2023-12-06 07:30:44"
    },
    {
      "urlChapter": "chapter-425",
      "dateUpdateChapter": "2023-12-06 07:30:42"
    },
    {
      "urlChapter": "chapter-424",
      "dateUpdateChapter": "2023-12-06 07:30:40"
    },
    {
      "urlChapter": "chapter-423",
      "dateUpdateChapter": "2023-12-06 07:30:38"
    },
    {
      "urlChapter": "chapter-422",
      "dateUpdateChapter": "2023-12-06 07:30:37"
    },
    {
      "urlChapter": "chapter-421",
      "dateUpdateChapter": "2023-12-06 07:30:35"
    },
    {
      "urlChapter": "chapter-420",
      "dateUpdateChapter": "2023-12-06 07:30:33"
    },
    {
      "urlChapter": "chapter-419",
      "dateUpdateChapter": "2023-12-06 07:30:31"
    },
    {
      "urlChapter": "chapter-418",
      "dateUpdateChapter": "2023-12-06 07:30:29"
    },
    {
      "urlChapter": "chapter-417",
      "dateUpdateChapter": "2023-12-06 07:30:28"
    },
    {
      "urlChapter": "chapter-416",
      "dateUpdateChapter": "2023-12-06 07:30:25"
    },
    {
      "urlChapter": "chapter-415",
      "dateUpdateChapter": "2023-12-06 07:30:23"
    },
    {
      "urlChapter": "chapter-414",
      "dateUpdateChapter": "2023-12-06 07:30:21"
    },
    {
      "urlChapter": "chapter-413",
      "dateUpdateChapter": "2023-12-06 07:30:19"
    },
    {
      "urlChapter": "chapter-412",
      "dateUpdateChapter": "2023-12-06 07:30:17"
    },
    {
      "urlChapter": "chapter-411",
      "dateUpdateChapter": "2023-12-06 07:30:16"
    },
    {
      "urlChapter": "chapter-410",
      "dateUpdateChapter": "2023-12-06 07:30:14"
    },
    {
      "urlChapter": "chapter-409",
      "dateUpdateChapter": "2023-12-06 07:30:12"
    },
    {
      "urlChapter": "chapter-408",
      "dateUpdateChapter": "2023-12-06 07:30:10"
    },
    {
      "urlChapter": "chapter-407",
      "dateUpdateChapter": "2023-12-06 07:30:08"
    },
    {
      "urlChapter": "chapter-406",
      "dateUpdateChapter": "2023-12-06 07:30:06"
    },
    {
      "urlChapter": "chapter-405",
      "dateUpdateChapter": "2023-12-06 07:30:05"
    },
    {
      "urlChapter": "chapter-404",
      "dateUpdateChapter": "2023-12-06 07:30:03"
    },
    {
      "urlChapter": "chapter-403",
      "dateUpdateChapter": "2023-12-06 07:30:01"
    },
    {
      "urlChapter": "chapter-402",
      "dateUpdateChapter": "2023-12-06 07:30:00"
    },
    {
      "urlChapter": "chapter-401",
      "dateUpdateChapter": "2023-12-06 07:29:57"
    },
    {
      "urlChapter": "chapter-400",
      "dateUpdateChapter": "2023-12-06 07:29:55"
    },
    {
      "urlChapter": "chapter-399",
      "dateUpdateChapter": "2023-12-06 07:29:54"
    },
    {
      "urlChapter": "chapter-398",
      "dateUpdateChapter": "2023-12-06 07:29:52"
    },
    {
      "urlChapter": "chapter-397",
      "dateUpdateChapter": "2023-12-06 07:29:50"
    },
    {
      "urlChapter": "chapter-396",
      "dateUpdateChapter": "2023-12-06 07:29:48"
    },
    {
      "urlChapter": "chapter-395",
      "dateUpdateChapter": "2023-12-06 07:29:47"
    },
    {
      "urlChapter": "chapter-394",
      "dateUpdateChapter": "2023-12-06 07:29:46"
    },
    {
      "urlChapter": "chapter-393",
      "dateUpdateChapter": "2023-12-06 07:29:44"
    },
    {
      "urlChapter": "chapter-392",
      "dateUpdateChapter": "2023-12-06 07:29:42"
    },
    {
      "urlChapter": "chapter-391",
      "dateUpdateChapter": "2023-12-06 07:29:40"
    },
    {
      "urlChapter": "chapter-390",
      "dateUpdateChapter": "2023-12-06 07:29:38"
    },
    {
      "urlChapter": "chapter-389",
      "dateUpdateChapter": "2023-12-06 07:29:37"
    },
    {
      "urlChapter": "chapter-388",
      "dateUpdateChapter": "2023-12-06 07:29:35"
    },
    {
      "urlChapter": "chapter-387",
      "dateUpdateChapter": "2023-12-06 07:29:33"
    },
    {
      "urlChapter": "chapter-386",
      "dateUpdateChapter": "2023-12-06 07:29:32"
    },
    {
      "urlChapter": "chapter-385",
      "dateUpdateChapter": "2023-12-06 07:29:29"
    },
    {
      "urlChapter": "chapter-384",
      "dateUpdateChapter": "2023-12-06 07:29:28"
    },
    {
      "urlChapter": "chapter-383",
      "dateUpdateChapter": "2023-12-06 07:29:26"
    },
    {
      "urlChapter": "chapter-382",
      "dateUpdateChapter": "2023-12-06 07:29:24"
    },
    {
      "urlChapter": "chapter-381",
      "dateUpdateChapter": "2023-12-06 07:29:22"
    },
    {
      "urlChapter": "chapter-380",
      "dateUpdateChapter": "2023-12-06 07:29:20"
    },
    {
      "urlChapter": "chapter-379",
      "dateUpdateChapter": "2023-12-06 07:29:19"
    },
    {
      "urlChapter": "chapter-378",
      "dateUpdateChapter": "2023-12-06 07:29:17"
    },
    {
      "urlChapter": "chapter-377",
      "dateUpdateChapter": "2023-12-06 07:29:15"
    },
    {
      "urlChapter": "chapter-376",
      "dateUpdateChapter": "2023-12-06 07:29:13"
    },
    {
      "urlChapter": "chapter-375",
      "dateUpdateChapter": "2023-12-06 07:29:11"
    },
    {
      "urlChapter": "chapter-374",
      "dateUpdateChapter": "2023-12-06 07:29:09"
    },
    {
      "urlChapter": "chapter-373",
      "dateUpdateChapter": "2023-12-06 07:29:07"
    },
    {
      "urlChapter": "chapter-372",
      "dateUpdateChapter": "2023-12-06 07:29:05"
    },
    {
      "urlChapter": "chapter-371",
      "dateUpdateChapter": "2023-12-06 07:29:02"
    },
    {
      "urlChapter": "chapter-370",
      "dateUpdateChapter": "2023-12-06 07:29:01"
    },
    {
      "urlChapter": "chapter-369",
      "dateUpdateChapter": "2023-12-06 07:28:59"
    },
    {
      "urlChapter": "chapter-368",
      "dateUpdateChapter": "2023-12-06 07:28:57"
    },
    {
      "urlChapter": "chapter-367",
      "dateUpdateChapter": "2023-12-06 07:28:55"
    },
    {
      "urlChapter": "chapter-366",
      "dateUpdateChapter": "2023-12-06 07:28:53"
    },
    {
      "urlChapter": "chapter-365",
      "dateUpdateChapter": "2023-12-06 07:28:51"
    },
    {
      "urlChapter": "chapter-364",
      "dateUpdateChapter": "2023-12-06 07:28:49"
    },
    {
      "urlChapter": "chapter-363",
      "dateUpdateChapter": "2023-12-06 07:28:47"
    },
    {
      "urlChapter": "chapter-362",
      "dateUpdateChapter": "2023-12-06 07:28:45"
    },
    {
      "urlChapter": "chapter-361",
      "dateUpdateChapter": "2023-12-06 07:28:43"
    },
    {
      "urlChapter": "chapter-360",
      "dateUpdateChapter": "2023-12-06 07:28:41"
    },
    {
      "urlChapter": "chapter-359",
      "dateUpdateChapter": "2023-12-06 07:28:39"
    },
    {
      "urlChapter": "chapter-358",
      "dateUpdateChapter": "2023-12-06 07:28:37"
    },
    {
      "urlChapter": "chapter-357",
      "dateUpdateChapter": "2023-12-06 07:28:35"
    },
    {
      "urlChapter": "chapter-356",
      "dateUpdateChapter": "2023-12-06 07:28:34"
    },
    {
      "urlChapter": "chapter-355",
      "dateUpdateChapter": "2023-12-06 07:28:32"
    },
    {
      "urlChapter": "chapter-354",
      "dateUpdateChapter": "2023-12-06 07:28:30"
    },
    {
      "urlChapter": "chapter-353",
      "dateUpdateChapter": "2023-12-06 07:28:28"
    },
    {
      "urlChapter": "chapter-352",
      "dateUpdateChapter": "2023-12-06 07:28:26"
    },
    {
      "urlChapter": "chapter-351",
      "dateUpdateChapter": "2023-12-06 07:28:24"
    },
    {
      "urlChapter": "chapter-350",
      "dateUpdateChapter": "2023-12-06 07:28:21"
    },
    {
      "urlChapter": "chapter-349",
      "dateUpdateChapter": "2023-12-06 07:28:19"
    },
    {
      "urlChapter": "chapter-348",
      "dateUpdateChapter": "2023-12-06 07:28:18"
    },
    {
      "urlChapter": "chapter-347",
      "dateUpdateChapter": "2023-12-06 07:28:15"
    },
    {
      "urlChapter": "chapter-346",
      "dateUpdateChapter": "2023-12-06 07:28:07"
    },
    {
      "urlChapter": "chapter-345",
      "dateUpdateChapter": "2023-12-06 07:28:05"
    },
    {
      "urlChapter": "chapter-344",
      "dateUpdateChapter": "2023-12-06 07:28:04"
    },
    {
      "urlChapter": "chapter-343",
      "dateUpdateChapter": "2023-12-06 07:28:02"
    },
    {
      "urlChapter": "chapter-342",
      "dateUpdateChapter": "2023-12-06 07:28:01"
    },
    {
      "urlChapter": "chapter-341",
      "dateUpdateChapter": "2023-12-06 07:27:59"
    },
    {
      "urlChapter": "chapter-340",
      "dateUpdateChapter": "2023-12-06 07:27:58"
    },
    {
      "urlChapter": "chapter-339",
      "dateUpdateChapter": "2023-12-06 07:27:56"
    },
    {
      "urlChapter": "chapter-338",
      "dateUpdateChapter": "2023-12-06 07:27:54"
    },
    {
      "urlChapter": "chapter-337",
      "dateUpdateChapter": "2023-12-06 07:27:52"
    },
    {
      "urlChapter": "chapter-336",
      "dateUpdateChapter": "2023-12-06 07:27:50"
    },
    {
      "urlChapter": "chapter-335",
      "dateUpdateChapter": "2023-12-06 07:27:47"
    },
    {
      "urlChapter": "chapter-334",
      "dateUpdateChapter": "2023-12-06 07:27:45"
    },
    {
      "urlChapter": "chapter-333",
      "dateUpdateChapter": "2023-12-06 07:27:44"
    },
    {
      "urlChapter": "chapter-332",
      "dateUpdateChapter": "2023-12-06 07:27:41"
    },
    {
      "urlChapter": "chapter-331",
      "dateUpdateChapter": "2023-12-06 07:27:39"
    },
    {
      "urlChapter": "chapter-330",
      "dateUpdateChapter": "2023-12-06 07:27:37"
    },
    {
      "urlChapter": "chapter-329",
      "dateUpdateChapter": "2023-12-06 07:27:36"
    },
    {
      "urlChapter": "chapter-328",
      "dateUpdateChapter": "2023-12-06 07:27:34"
    },
    {
      "urlChapter": "chapter-327",
      "dateUpdateChapter": "2023-12-06 07:27:32"
    },
    {
      "urlChapter": "chapter-326",
      "dateUpdateChapter": "2023-12-06 07:27:29"
    },
    {
      "urlChapter": "chapter-325",
      "dateUpdateChapter": "2023-12-06 07:27:28"
    },
    {
      "urlChapter": "chapter-324",
      "dateUpdateChapter": "2023-12-06 07:27:23"
    },
    {
      "urlChapter": "chapter-323",
      "dateUpdateChapter": "2023-12-06 07:27:21"
    },
    {
      "urlChapter": "chapter-322",
      "dateUpdateChapter": "2023-12-06 07:27:20"
    },
    {
      "urlChapter": "chapter-321",
      "dateUpdateChapter": "2023-12-06 07:27:18"
    },
    {
      "urlChapter": "chapter-320",
      "dateUpdateChapter": "2023-12-06 07:27:16"
    },
    {
      "urlChapter": "chapter-319",
      "dateUpdateChapter": "2023-12-06 07:27:13"
    },
    {
      "urlChapter": "chapter-318",
      "dateUpdateChapter": "2023-12-06 07:27:11"
    },
    {
      "urlChapter": "chapter-317",
      "dateUpdateChapter": "2023-12-06 07:27:09"
    },
    {
      "urlChapter": "chapter-316",
      "dateUpdateChapter": "2023-12-06 07:27:07"
    },
    {
      "urlChapter": "chapter-315",
      "dateUpdateChapter": "2023-12-06 07:27:05"
    },
    {
      "urlChapter": "chapter-314",
      "dateUpdateChapter": "2023-12-06 07:27:03"
    },
    {
      "urlChapter": "chapter-313",
      "dateUpdateChapter": "2023-12-06 07:27:02"
    },
    {
      "urlChapter": "chapter-312",
      "dateUpdateChapter": "2023-12-06 07:27:00"
    },
    {
      "urlChapter": "chapter-311",
      "dateUpdateChapter": "2023-12-06 07:26:58"
    },
    {
      "urlChapter": "chapter-310",
      "dateUpdateChapter": "2023-12-06 07:26:57"
    },
    {
      "urlChapter": "chapter-309",
      "dateUpdateChapter": "2023-12-06 07:26:55"
    },
    {
      "urlChapter": "chapter-308",
      "dateUpdateChapter": "2023-12-06 07:26:53"
    },
    {
      "urlChapter": "chapter-307",
      "dateUpdateChapter": "2023-12-06 07:26:52"
    },
    {
      "urlChapter": "chapter-306",
      "dateUpdateChapter": "2023-12-06 07:26:50"
    },
    {
      "urlChapter": "chapter-305",
      "dateUpdateChapter": "2023-12-06 07:26:48"
    },
    {
      "urlChapter": "chapter-304",
      "dateUpdateChapter": "2023-12-06 07:26:46"
    },
    {
      "urlChapter": "chapter-303",
      "dateUpdateChapter": "2023-12-06 07:26:45"
    },
    {
      "urlChapter": "chapter-302",
      "dateUpdateChapter": "2023-12-06 07:26:43"
    },
    {
      "urlChapter": "chapter-301",
      "dateUpdateChapter": "2023-12-06 07:26:42"
    },
    {
      "urlChapter": "chapter-300",
      "dateUpdateChapter": "2023-12-06 07:26:40"
    },
    {
      "urlChapter": "chapter-299",
      "dateUpdateChapter": "2023-12-06 07:26:38"
    },
    {
      "urlChapter": "chapter-298",
      "dateUpdateChapter": "2023-12-06 07:26:36"
    },
    {
      "urlChapter": "chapter-297",
      "dateUpdateChapter": "2023-12-06 07:26:34"
    },
    {
      "urlChapter": "chapter-296",
      "dateUpdateChapter": "2023-12-06 07:26:32"
    },
    {
      "urlChapter": "chapter-295",
      "dateUpdateChapter": "2023-12-06 07:26:31"
    },
    {
      "urlChapter": "chapter-294",
      "dateUpdateChapter": "2023-12-06 07:26:29"
    },
    {
      "urlChapter": "chapter-293",
      "dateUpdateChapter": "2023-12-06 07:26:28"
    },
    {
      "urlChapter": "chapter-292",
      "dateUpdateChapter": "2023-12-06 07:26:26"
    },
    {
      "urlChapter": "chapter-291",
      "dateUpdateChapter": "2023-12-06 07:26:24"
    },
    {
      "urlChapter": "chapter-290",
      "dateUpdateChapter": "2023-12-06 07:26:23"
    },
    {
      "urlChapter": "chapter-289",
      "dateUpdateChapter": "2023-12-06 07:26:21"
    },
    {
      "urlChapter": "chapter-288",
      "dateUpdateChapter": "2023-12-06 07:26:20"
    },
    {
      "urlChapter": "chapter-287",
      "dateUpdateChapter": "2023-12-06 07:26:18"
    },
    {
      "urlChapter": "chapter-286",
      "dateUpdateChapter": "2023-12-06 07:26:16"
    },
    {
      "urlChapter": "chapter-285",
      "dateUpdateChapter": "2023-12-06 07:26:14"
    },
    {
      "urlChapter": "chapter-284",
      "dateUpdateChapter": "2023-12-06 07:26:13"
    },
    {
      "urlChapter": "chapter-283",
      "dateUpdateChapter": "2023-12-06 07:26:11"
    },
    {
      "urlChapter": "chapter-282",
      "dateUpdateChapter": "2023-12-06 07:26:09"
    },
    {
      "urlChapter": "chapter-281",
      "dateUpdateChapter": "2023-12-06 07:26:07"
    },
    {
      "urlChapter": "chapter-280",
      "dateUpdateChapter": "2023-12-06 07:26:05"
    },
    {
      "urlChapter": "chapter-279",
      "dateUpdateChapter": "2023-12-06 07:26:03"
    },
    {
      "urlChapter": "chapter-278",
      "dateUpdateChapter": "2023-12-06 07:26:01"
    },
    {
      "urlChapter": "chapter-277",
      "dateUpdateChapter": "2023-12-06 07:26:00"
    },
    {
      "urlChapter": "chapter-276",
      "dateUpdateChapter": "2023-12-06 07:25:58"
    },
    {
      "urlChapter": "chapter-275",
      "dateUpdateChapter": "2023-12-06 07:25:56"
    },
    {
      "urlChapter": "chapter-274",
      "dateUpdateChapter": "2023-12-06 07:25:55"
    },
    {
      "urlChapter": "chapter-273",
      "dateUpdateChapter": "2023-12-06 07:25:53"
    },
    {
      "urlChapter": "chapter-272",
      "dateUpdateChapter": "2023-12-06 07:25:51"
    },
    {
      "urlChapter": "chapter-271",
      "dateUpdateChapter": "2023-12-06 07:25:50"
    },
    {
      "urlChapter": "chapter-270",
      "dateUpdateChapter": "2023-12-06 07:25:49"
    },
    {
      "urlChapter": "chapter-269",
      "dateUpdateChapter": "2023-12-06 07:25:47"
    },
    {
      "urlChapter": "chapter-268",
      "dateUpdateChapter": "2023-12-06 07:25:45"
    },
    {
      "urlChapter": "chapter-267",
      "dateUpdateChapter": "2023-12-06 07:25:43"
    },
    {
      "urlChapter": "chapter-266",
      "dateUpdateChapter": "2023-12-06 07:25:41"
    },
    {
      "urlChapter": "chapter-265",
      "dateUpdateChapter": "2023-12-06 07:25:39"
    },
    {
      "urlChapter": "chapter-264",
      "dateUpdateChapter": "2023-12-06 07:25:37"
    },
    {
      "urlChapter": "chapter-263",
      "dateUpdateChapter": "2023-12-06 07:25:36"
    },
    {
      "urlChapter": "chapter-262",
      "dateUpdateChapter": "2023-12-06 07:25:34"
    },
    {
      "urlChapter": "chapter-261",
      "dateUpdateChapter": "2023-12-06 07:25:33"
    },
    {
      "urlChapter": "chapter-260",
      "dateUpdateChapter": "2023-12-06 07:25:30"
    },
    {
      "urlChapter": "chapter-259",
      "dateUpdateChapter": "2023-12-06 07:25:29"
    },
    {
      "urlChapter": "chapter-258",
      "dateUpdateChapter": "2023-12-06 07:25:27"
    },
    {
      "urlChapter": "chapter-257",
      "dateUpdateChapter": "2023-12-06 07:25:26"
    },
    {
      "urlChapter": "chapter-256",
      "dateUpdateChapter": "2023-12-06 07:25:24"
    },
    {
      "urlChapter": "chapter-255",
      "dateUpdateChapter": "2023-12-06 07:25:22"
    },
    {
      "urlChapter": "chapter-254",
      "dateUpdateChapter": "2023-12-06 07:25:20"
    },
    {
      "urlChapter": "chapter-253",
      "dateUpdateChapter": "2023-12-06 07:25:19"
    },
    {
      "urlChapter": "chapter-252",
      "dateUpdateChapter": "2023-12-06 07:25:17"
    },
    {
      "urlChapter": "chapter-251",
      "dateUpdateChapter": "2023-12-06 07:25:15"
    },
    {
      "urlChapter": "chapter-250",
      "dateUpdateChapter": "2023-12-06 07:25:14"
    },
    {
      "urlChapter": "chapter-249",
      "dateUpdateChapter": "2023-12-06 07:25:12"
    },
    {
      "urlChapter": "chapter-248",
      "dateUpdateChapter": "2023-12-06 07:25:10"
    },
    {
      "urlChapter": "chapter-247",
      "dateUpdateChapter": "2023-12-06 07:25:08"
    },
    {
      "urlChapter": "chapter-246",
      "dateUpdateChapter": "2023-12-06 07:25:06"
    },
    {
      "urlChapter": "chapter-245",
      "dateUpdateChapter": "2023-12-06 07:25:04"
    },
    {
      "urlChapter": "chapter-244",
      "dateUpdateChapter": "2023-12-06 07:25:02"
    },
    {
      "urlChapter": "chapter-243",
      "dateUpdateChapter": "2023-12-06 07:25:01"
    },
    {
      "urlChapter": "chapter-242",
      "dateUpdateChapter": "2023-12-06 07:25:00"
    },
    {
      "urlChapter": "chapter-241",
      "dateUpdateChapter": "2023-12-06 07:24:58"
    },
    {
      "urlChapter": "chapter-240",
      "dateUpdateChapter": "2023-12-06 07:24:56"
    },
    {
      "urlChapter": "chapter-239",
      "dateUpdateChapter": "2023-12-06 07:24:54"
    },
    {
      "urlChapter": "chapter-238",
      "dateUpdateChapter": "2023-12-06 07:24:53"
    },
    {
      "urlChapter": "chapter-237",
      "dateUpdateChapter": "2023-12-06 07:24:50"
    },
    {
      "urlChapter": "chapter-236",
      "dateUpdateChapter": "2023-12-06 07:24:49"
    },
    {
      "urlChapter": "chapter-235",
      "dateUpdateChapter": "2023-12-06 07:24:47"
    },
    {
      "urlChapter": "chapter-234",
      "dateUpdateChapter": "2023-12-06 07:24:45"
    },
    {
      "urlChapter": "chapter-233",
      "dateUpdateChapter": "2023-12-06 07:24:44"
    },
    {
      "urlChapter": "chapter-232",
      "dateUpdateChapter": "2023-12-06 07:24:42"
    },
    {
      "urlChapter": "chapter-231",
      "dateUpdateChapter": "2023-12-06 07:24:40"
    },
    {
      "urlChapter": "chapter-230",
      "dateUpdateChapter": "2023-12-06 07:24:38"
    },
    {
      "urlChapter": "chapter-229",
      "dateUpdateChapter": "2023-12-06 07:24:36"
    },
    {
      "urlChapter": "chapter-228",
      "dateUpdateChapter": "2023-12-06 07:24:34"
    },
    {
      "urlChapter": "chapter-227",
      "dateUpdateChapter": "2023-12-06 07:24:32"
    },
    {
      "urlChapter": "chapter-226",
      "dateUpdateChapter": "2023-12-06 07:24:30"
    },
    {
      "urlChapter": "chapter-225",
      "dateUpdateChapter": "2023-12-06 07:24:29"
    },
    {
      "urlChapter": "chapter-224",
      "dateUpdateChapter": "2023-12-06 07:24:27"
    },
    {
      "urlChapter": "chapter-223",
      "dateUpdateChapter": "2023-12-06 07:24:24"
    },
    {
      "urlChapter": "chapter-222",
      "dateUpdateChapter": "2023-12-06 07:24:23"
    },
    {
      "urlChapter": "chapter-221",
      "dateUpdateChapter": "2023-12-06 07:24:21"
    },
    {
      "urlChapter": "chapter-220",
      "dateUpdateChapter": "2023-12-06 07:24:19"
    },
    {
      "urlChapter": "chapter-219",
      "dateUpdateChapter": "2023-12-06 07:24:17"
    },
    {
      "urlChapter": "chapter-218",
      "dateUpdateChapter": "2023-12-06 07:24:15"
    },
    {
      "urlChapter": "chapter-217",
      "dateUpdateChapter": "2023-12-06 07:24:14"
    },
    {
      "urlChapter": "chapter-216",
      "dateUpdateChapter": "2023-12-06 07:24:12"
    },
    {
      "urlChapter": "chapter-215",
      "dateUpdateChapter": "2023-12-06 07:24:10"
    },
    {
      "urlChapter": "chapter-214",
      "dateUpdateChapter": "2023-12-06 07:24:08"
    },
    {
      "urlChapter": "chapter-213",
      "dateUpdateChapter": "2023-12-06 07:24:07"
    },
    {
      "urlChapter": "chapter-212",
      "dateUpdateChapter": "2023-12-06 07:24:05"
    },
    {
      "urlChapter": "chapter-211",
      "dateUpdateChapter": "2023-12-06 07:24:04"
    },
    {
      "urlChapter": "chapter-210",
      "dateUpdateChapter": "2023-12-06 07:24:02"
    },
    {
      "urlChapter": "chapter-209",
      "dateUpdateChapter": "2023-12-06 07:24:01"
    },
    {
      "urlChapter": "chapter-208",
      "dateUpdateChapter": "2023-12-06 07:23:59"
    },
    {
      "urlChapter": "chapter-207",
      "dateUpdateChapter": "2023-12-06 07:23:58"
    },
    {
      "urlChapter": "chapter-206",
      "dateUpdateChapter": "2023-12-06 07:23:56"
    },
    {
      "urlChapter": "chapter-205",
      "dateUpdateChapter": "2023-12-06 07:23:54"
    },
    {
      "urlChapter": "chapter-204",
      "dateUpdateChapter": "2023-12-06 07:23:53"
    },
    {
      "urlChapter": "chapter-203",
      "dateUpdateChapter": "2023-12-06 07:23:50"
    },
    {
      "urlChapter": "chapter-202",
      "dateUpdateChapter": "2023-12-06 07:23:48"
    },
    {
      "urlChapter": "chapter-201",
      "dateUpdateChapter": "2023-12-06 07:23:47"
    },
    {
      "urlChapter": "chapter-200",
      "dateUpdateChapter": "2023-12-06 07:23:45"
    },
    {
      "urlChapter": "chapter-199",
      "dateUpdateChapter": "2023-12-06 07:23:43"
    },
    {
      "urlChapter": "chapter-198",
      "dateUpdateChapter": "2023-12-06 07:23:41"
    },
    {
      "urlChapter": "chapter-197",
      "dateUpdateChapter": "2023-12-06 07:23:39"
    },
    {
      "urlChapter": "chapter-196",
      "dateUpdateChapter": "2023-12-06 07:23:37"
    },
    {
      "urlChapter": "chapter-195",
      "dateUpdateChapter": "2023-12-06 07:23:34"
    },
    {
      "urlChapter": "chapter-194",
      "dateUpdateChapter": "2023-12-06 07:23:32"
    },
    {
      "urlChapter": "chapter-193",
      "dateUpdateChapter": "2023-12-06 07:23:30"
    },
    {
      "urlChapter": "chapter-192",
      "dateUpdateChapter": "2023-12-06 07:23:28"
    },
    {
      "urlChapter": "chapter-191",
      "dateUpdateChapter": "2023-12-06 07:23:27"
    },
    {
      "urlChapter": "chapter-190",
      "dateUpdateChapter": "2023-12-06 07:23:25"
    },
    {
      "urlChapter": "chapter-189",
      "dateUpdateChapter": "2023-12-06 07:23:23"
    },
    {
      "urlChapter": "chapter-188",
      "dateUpdateChapter": "2023-12-06 07:23:21"
    },
    {
      "urlChapter": "chapter-187",
      "dateUpdateChapter": "2023-12-06 07:23:18"
    },
    {
      "urlChapter": "chapter-186",
      "dateUpdateChapter": "2023-12-06 07:23:17"
    },
    {
      "urlChapter": "chapter-185",
      "dateUpdateChapter": "2023-12-06 07:23:14"
    },
    {
      "urlChapter": "chapter-184",
      "dateUpdateChapter": "2023-12-06 07:23:12"
    },
    {
      "urlChapter": "chapter-183",
      "dateUpdateChapter": "2023-12-06 07:23:10"
    },
    {
      "urlChapter": "chapter-182",
      "dateUpdateChapter": "2023-12-06 07:23:08"
    },
    {
      "urlChapter": "chapter-181",
      "dateUpdateChapter": "2023-12-06 07:23:06"
    },
    {
      "urlChapter": "chapter-180",
      "dateUpdateChapter": "2023-12-06 07:23:04"
    },
    {
      "urlChapter": "chapter-179",
      "dateUpdateChapter": "2023-12-06 07:23:01"
    },
    {
      "urlChapter": "chapter-178",
      "dateUpdateChapter": "2023-12-06 07:22:59"
    },
    {
      "urlChapter": "chapter-177",
      "dateUpdateChapter": "2023-12-06 07:22:57"
    },
    {
      "urlChapter": "chapter-176",
      "dateUpdateChapter": "2023-12-06 07:22:55"
    },
    {
      "urlChapter": "chapter-175",
      "dateUpdateChapter": "2023-12-06 07:22:53"
    },
    {
      "urlChapter": "chapter-174",
      "dateUpdateChapter": "2023-12-06 07:22:51"
    },
    {
      "urlChapter": "chapter-173",
      "dateUpdateChapter": "2023-12-06 07:22:49"
    },
    {
      "urlChapter": "chapter-172",
      "dateUpdateChapter": "2023-12-06 07:22:46"
    },
    {
      "urlChapter": "chapter-171",
      "dateUpdateChapter": "2023-12-06 07:22:45"
    },
    {
      "urlChapter": "chapter-170",
      "dateUpdateChapter": "2023-12-06 07:22:43"
    },
    {
      "urlChapter": "chapter-169",
      "dateUpdateChapter": "2023-12-06 07:22:41"
    },
    {
      "urlChapter": "chapter-168",
      "dateUpdateChapter": "2023-12-06 07:22:39"
    },
    {
      "urlChapter": "chapter-167",
      "dateUpdateChapter": "2023-12-06 07:22:37"
    },
    {
      "urlChapter": "chapter-166",
      "dateUpdateChapter": "2023-12-06 07:22:36"
    },
    {
      "urlChapter": "chapter-165",
      "dateUpdateChapter": "2023-12-06 07:22:34"
    },
    {
      "urlChapter": "chapter-164",
      "dateUpdateChapter": "2023-12-06 07:22:32"
    },
    {
      "urlChapter": "chapter-163",
      "dateUpdateChapter": "2023-12-06 07:22:30"
    },
    {
      "urlChapter": "chapter-162",
      "dateUpdateChapter": "2023-12-06 07:22:27"
    },
    {
      "urlChapter": "chapter-161",
      "dateUpdateChapter": "2023-12-06 07:22:25"
    },
    {
      "urlChapter": "chapter-160",
      "dateUpdateChapter": "2023-12-06 07:22:23"
    },
    {
      "urlChapter": "chapter-159",
      "dateUpdateChapter": "2023-12-06 07:22:21"
    },
    {
      "urlChapter": "chapter-158",
      "dateUpdateChapter": "2023-12-06 07:22:19"
    },
    {
      "urlChapter": "chapter-157",
      "dateUpdateChapter": "2023-12-06 07:22:17"
    },
    {
      "urlChapter": "chapter-156",
      "dateUpdateChapter": "2023-12-06 07:22:16"
    },
    {
      "urlChapter": "chapter-155",
      "dateUpdateChapter": "2023-12-06 07:22:14"
    },
    {
      "urlChapter": "chapter-154",
      "dateUpdateChapter": "2023-12-06 07:22:12"
    },
    {
      "urlChapter": "chapter-153",
      "dateUpdateChapter": "2023-12-06 07:22:10"
    },
    {
      "urlChapter": "chapter-152",
      "dateUpdateChapter": "2023-12-06 07:22:08"
    },
    {
      "urlChapter": "chapter-151",
      "dateUpdateChapter": "2023-12-06 07:22:06"
    },
    {
      "urlChapter": "chapter-150",
      "dateUpdateChapter": "2023-12-06 07:22:04"
    },
    {
      "urlChapter": "chapter-149",
      "dateUpdateChapter": "2023-12-06 07:22:01"
    },
    {
      "urlChapter": "chapter-148",
      "dateUpdateChapter": "2023-12-06 07:22:00"
    },
    {
      "urlChapter": "chapter-147",
      "dateUpdateChapter": "2023-12-06 07:21:57"
    },
    {
      "urlChapter": "chapter-146",
      "dateUpdateChapter": "2023-12-06 07:21:56"
    },
    {
      "urlChapter": "chapter-145",
      "dateUpdateChapter": "2023-12-06 07:21:54"
    },
    {
      "urlChapter": "chapter-144",
      "dateUpdateChapter": "2023-12-06 07:21:51"
    },
    {
      "urlChapter": "chapter-143",
      "dateUpdateChapter": "2023-12-06 07:21:49"
    },
    {
      "urlChapter": "chapter-142",
      "dateUpdateChapter": "2023-12-06 07:21:47"
    },
    {
      "urlChapter": "chapter-141",
      "dateUpdateChapter": "2023-12-06 07:21:46"
    },
    {
      "urlChapter": "chapter-140",
      "dateUpdateChapter": "2023-12-06 07:21:44"
    },
    {
      "urlChapter": "chapter-139",
      "dateUpdateChapter": "2023-12-06 07:21:43"
    },
    {
      "urlChapter": "chapter-138",
      "dateUpdateChapter": "2023-12-06 07:21:41"
    },
    {
      "urlChapter": "chapter-137",
      "dateUpdateChapter": "2023-12-06 07:21:39"
    },
    {
      "urlChapter": "chapter-136",
      "dateUpdateChapter": "2023-12-06 07:21:37"
    },
    {
      "urlChapter": "chapter-135",
      "dateUpdateChapter": "2023-12-06 07:21:34"
    },
    {
      "urlChapter": "chapter-134",
      "dateUpdateChapter": "2023-12-06 07:21:32"
    },
    {
      "urlChapter": "chapter-133",
      "dateUpdateChapter": "2023-12-06 07:21:30"
    },
    {
      "urlChapter": "chapter-132",
      "dateUpdateChapter": "2023-12-06 07:21:27"
    },
    {
      "urlChapter": "chapter-131",
      "dateUpdateChapter": "2023-12-06 07:21:25"
    },
    {
      "urlChapter": "chapter-130",
      "dateUpdateChapter": "2023-12-06 07:21:23"
    },
    {
      "urlChapter": "chapter-129",
      "dateUpdateChapter": "2023-12-06 07:21:21"
    },
    {
      "urlChapter": "chapter-128",
      "dateUpdateChapter": "2023-12-06 07:21:19"
    },
    {
      "urlChapter": "chapter-127",
      "dateUpdateChapter": "2023-12-06 07:21:17"
    },
    {
      "urlChapter": "chapter-126",
      "dateUpdateChapter": "2023-12-06 07:21:15"
    },
    {
      "urlChapter": "chapter-125",
      "dateUpdateChapter": "2023-12-06 07:21:13"
    },
    {
      "urlChapter": "chapter-124",
      "dateUpdateChapter": "2023-12-06 07:21:11"
    },
    {
      "urlChapter": "chapter-123",
      "dateUpdateChapter": "2023-12-06 07:21:09"
    },
    {
      "urlChapter": "chapter-122",
      "dateUpdateChapter": "2023-12-06 07:21:07"
    },
    {
      "urlChapter": "chapter-121",
      "dateUpdateChapter": "2023-12-06 07:21:05"
    },
    {
      "urlChapter": "chapter-120",
      "dateUpdateChapter": "2023-12-06 07:21:04"
    },
    {
      "urlChapter": "chapter-119",
      "dateUpdateChapter": "2023-12-06 07:21:02"
    },
    {
      "urlChapter": "chapter-118",
      "dateUpdateChapter": "2023-12-06 07:21:00"
    },
    {
      "urlChapter": "chapter-117",
      "dateUpdateChapter": "2023-12-06 07:20:58"
    },
    {
      "urlChapter": "chapter-116",
      "dateUpdateChapter": "2023-12-06 07:20:57"
    },
    {
      "urlChapter": "chapter-115",
      "dateUpdateChapter": "2023-12-06 07:20:55"
    },
    {
      "urlChapter": "chapter-114",
      "dateUpdateChapter": "2023-12-06 07:20:53"
    },
    {
      "urlChapter": "chapter-113",
      "dateUpdateChapter": "2023-12-06 07:20:52"
    },
    {
      "urlChapter": "chapter-112",
      "dateUpdateChapter": "2023-12-06 07:20:50"
    },
    {
      "urlChapter": "chapter-111",
      "dateUpdateChapter": "2023-12-06 07:20:48"
    },
    {
      "urlChapter": "chapter-110",
      "dateUpdateChapter": "2023-12-06 07:20:46"
    },
    {
      "urlChapter": "chapter-109",
      "dateUpdateChapter": "2023-12-06 07:20:44"
    },
    {
      "urlChapter": "chapter-108",
      "dateUpdateChapter": "2023-12-06 07:20:42"
    },
    {
      "urlChapter": "chapter-107",
      "dateUpdateChapter": "2023-12-06 07:20:40"
    },
    {
      "urlChapter": "chapter-106",
      "dateUpdateChapter": "2023-12-06 07:20:38"
    },
    {
      "urlChapter": "chapter-105",
      "dateUpdateChapter": "2023-12-06 07:20:36"
    },
    {
      "urlChapter": "chapter-104",
      "dateUpdateChapter": "2023-12-06 07:20:34"
    },
    {
      "urlChapter": "chapter-103",
      "dateUpdateChapter": "2023-12-06 07:20:32"
    },
    {
      "urlChapter": "chapter-102",
      "dateUpdateChapter": "2023-12-06 07:20:30"
    },
    {
      "urlChapter": "chapter-101",
      "dateUpdateChapter": "2023-12-06 07:20:29"
    },
    {
      "urlChapter": "chapter-100",
      "dateUpdateChapter": "2023-12-06 07:20:27"
    },
    {
      "urlChapter": "chapter-99",
      "dateUpdateChapter": "2023-12-06 07:20:24"
    },
    {
      "urlChapter": "chapter-98",
      "dateUpdateChapter": "2023-12-06 07:20:22"
    },
    {
      "urlChapter": "chapter-97",
      "dateUpdateChapter": "2023-12-06 07:20:20"
    },
    {
      "urlChapter": "chapter-96",
      "dateUpdateChapter": "2023-12-06 07:20:18"
    },
    {
      "urlChapter": "chapter-95",
      "dateUpdateChapter": "2023-12-06 07:20:15"
    },
    {
      "urlChapter": "chapter-94",
      "dateUpdateChapter": "2023-12-06 07:20:14"
    },
    {
      "urlChapter": "chapter-93",
      "dateUpdateChapter": "2023-12-06 07:20:12"
    },
    {
      "urlChapter": "chapter-92",
      "dateUpdateChapter": "2023-12-06 07:20:10"
    },
    {
      "urlChapter": "chapter-91",
      "dateUpdateChapter": "2023-12-06 07:20:08"
    },
    {
      "urlChapter": "chapter-90",
      "dateUpdateChapter": "2023-12-06 07:20:06"
    },
    {
      "urlChapter": "chapter-89",
      "dateUpdateChapter": "2023-12-06 07:20:04"
    },
    {
      "urlChapter": "chapter-88",
      "dateUpdateChapter": "2023-12-06 07:20:03"
    },
    {
      "urlChapter": "chapter-87",
      "dateUpdateChapter": "2023-12-06 07:20:01"
    },
    {
      "urlChapter": "chapter-86",
      "dateUpdateChapter": "2023-12-06 07:19:59"
    },
    {
      "urlChapter": "chapter-85",
      "dateUpdateChapter": "2023-12-06 07:19:57"
    },
    {
      "urlChapter": "chapter-84",
      "dateUpdateChapter": "2023-12-06 07:19:56"
    },
    {
      "urlChapter": "chapter-83",
      "dateUpdateChapter": "2023-12-06 07:19:54"
    },
    {
      "urlChapter": "chapter-82",
      "dateUpdateChapter": "2023-12-06 07:19:52"
    },
    {
      "urlChapter": "chapter-81",
      "dateUpdateChapter": "2023-12-06 07:19:50"
    },
    {
      "urlChapter": "chapter-80",
      "dateUpdateChapter": "2023-12-06 07:19:48"
    },
    {
      "urlChapter": "chapter-79",
      "dateUpdateChapter": "2023-12-06 07:19:46"
    },
    {
      "urlChapter": "chapter-78",
      "dateUpdateChapter": "2023-12-06 07:19:44"
    },
    {
      "urlChapter": "chapter-77",
      "dateUpdateChapter": "2023-12-06 07:19:42"
    },
    {
      "urlChapter": "chapter-76",
      "dateUpdateChapter": "2023-12-06 07:19:41"
    },
    {
      "urlChapter": "chapter-75",
      "dateUpdateChapter": "2023-12-06 07:19:39"
    },
    {
      "urlChapter": "chapter-74",
      "dateUpdateChapter": "2023-12-06 07:19:37"
    },
    {
      "urlChapter": "chapter-73",
      "dateUpdateChapter": "2023-12-06 07:19:35"
    },
    {
      "urlChapter": "chapter-72",
      "dateUpdateChapter": "2023-12-06 07:19:33"
    },
    {
      "urlChapter": "chapter-71",
      "dateUpdateChapter": "2023-12-06 07:19:32"
    },
    {
      "urlChapter": "chapter-70",
      "dateUpdateChapter": "2023-12-06 07:19:30"
    },
    {
      "urlChapter": "chapter-69",
      "dateUpdateChapter": "2023-12-06 07:19:28"
    },
    {
      "urlChapter": "chapter-68",
      "dateUpdateChapter": "2023-12-06 07:19:26"
    },
    {
      "urlChapter": "chapter-67",
      "dateUpdateChapter": "2023-12-06 07:19:24"
    },
    {
      "urlChapter": "chapter-66",
      "dateUpdateChapter": "2023-12-06 07:19:22"
    },
    {
      "urlChapter": "chapter-65",
      "dateUpdateChapter": "2023-12-06 07:19:21"
    },
    {
      "urlChapter": "chapter-64",
      "dateUpdateChapter": "2023-12-06 07:19:19"
    },
    {
      "urlChapter": "chapter-63",
      "dateUpdateChapter": "2023-12-06 07:19:17"
    },
    {
      "urlChapter": "chapter-62",
      "dateUpdateChapter": "2023-12-06 07:19:15"
    },
    {
      "urlChapter": "chapter-61",
      "dateUpdateChapter": "2023-12-06 07:19:13"
    },
    {
      "urlChapter": "chapter-60",
      "dateUpdateChapter": "2023-12-06 07:19:11"
    },
    {
      "urlChapter": "chapter-59",
      "dateUpdateChapter": "2023-12-06 07:19:09"
    },
    {
      "urlChapter": "chapter-58",
      "dateUpdateChapter": "2023-12-06 07:19:08"
    },
    {
      "urlChapter": "chapter-57",
      "dateUpdateChapter": "2023-12-06 07:19:06"
    },
    {
      "urlChapter": "chapter-56",
      "dateUpdateChapter": "2023-12-06 07:19:04"
    },
    {
      "urlChapter": "chapter-55",
      "dateUpdateChapter": "2023-12-06 07:19:02"
    },
    {
      "urlChapter": "chapter-54",
      "dateUpdateChapter": "2023-12-06 07:19:00"
    },
    {
      "urlChapter": "chapter-53",
      "dateUpdateChapter": "2023-12-06 07:18:58"
    },
    {
      "urlChapter": "chapter-52",
      "dateUpdateChapter": "2023-12-06 07:18:57"
    },
    {
      "urlChapter": "chapter-51",
      "dateUpdateChapter": "2023-12-06 07:18:55"
    },
    {
      "urlChapter": "chapter-50",
      "dateUpdateChapter": "2023-12-06 07:18:53"
    },
    {
      "urlChapter": "chapter-49",
      "dateUpdateChapter": "2023-12-06 07:18:52"
    },
    {
      "urlChapter": "chapter-48",
      "dateUpdateChapter": "2023-12-06 07:18:50"
    },
    {
      "urlChapter": "chapter-47",
      "dateUpdateChapter": "2023-12-06 07:18:48"
    },
    {
      "urlChapter": "chapter-46",
      "dateUpdateChapter": "2023-12-06 07:18:46"
    },
    {
      "urlChapter": "chapter-45",
      "dateUpdateChapter": "2023-12-06 07:18:44"
    },
    {
      "urlChapter": "chapter-44",
      "dateUpdateChapter": "2023-12-06 07:18:42"
    },
    {
      "urlChapter": "chapter-43",
      "dateUpdateChapter": "2023-12-06 07:18:40"
    },
    {
      "urlChapter": "chapter-42",
      "dateUpdateChapter": "2023-12-06 07:18:39"
    },
    {
      "urlChapter": "chapter-41",
      "dateUpdateChapter": "2023-12-06 07:18:37"
    },
    {
      "urlChapter": "chapter-40",
      "dateUpdateChapter": "2023-12-06 07:18:35"
    },
    {
      "urlChapter": "chapter-39",
      "dateUpdateChapter": "2023-12-06 07:18:34"
    },
    {
      "urlChapter": "chapter-38",
      "dateUpdateChapter": "2023-12-06 07:18:32"
    },
    {
      "urlChapter": "chapter-37",
      "dateUpdateChapter": "2023-12-06 07:18:30"
    },
    {
      "urlChapter": "chapter-36",
      "dateUpdateChapter": "2023-12-06 07:18:28"
    },
    {
      "urlChapter": "chapter-35",
      "dateUpdateChapter": "2023-12-06 07:18:25"
    },
    {
      "urlChapter": "chapter-34",
      "dateUpdateChapter": "2023-12-06 07:18:24"
    },
    {
      "urlChapter": "chapter-33",
      "dateUpdateChapter": "2023-12-06 07:18:22"
    },
    {
      "urlChapter": "chapter-32",
      "dateUpdateChapter": "2023-12-06 07:18:20"
    },
    {
      "urlChapter": "chapter-31",
      "dateUpdateChapter": "2023-12-06 07:18:18"
    },
    {
      "urlChapter": "chapter-30",
      "dateUpdateChapter": "2023-12-06 07:18:16"
    },
    {
      "urlChapter": "chapter-29",
      "dateUpdateChapter": "2023-12-06 07:18:13"
    },
    {
      "urlChapter": "chapter-28",
      "dateUpdateChapter": "2023-12-06 07:18:11"
    },
    {
      "urlChapter": "chapter-27",
      "dateUpdateChapter": "2023-12-06 07:18:10"
    },
    {
      "urlChapter": "chapter-26",
      "dateUpdateChapter": "2023-12-06 07:18:07"
    },
    {
      "urlChapter": "chapter-25",
      "dateUpdateChapter": "2023-12-06 07:18:06"
    },
    {
      "urlChapter": "chapter-24",
      "dateUpdateChapter": "2023-12-06 07:18:04"
    },
    {
      "urlChapter": "chapter-23",
      "dateUpdateChapter": "2023-12-06 07:18:02"
    },
    {
      "urlChapter": "chapter-22",
      "dateUpdateChapter": "2023-12-06 07:18:01"
    },
    {
      "urlChapter": "chapter-21",
      "dateUpdateChapter": "2023-12-06 07:17:59"
    },
    {
      "urlChapter": "chapter-20",
      "dateUpdateChapter": "2023-12-06 07:17:57"
    },
    {
      "urlChapter": "chapter-19",
      "dateUpdateChapter": "2023-12-06 07:17:55"
    },
    {
      "urlChapter": "chapter-18",
      "dateUpdateChapter": "2023-12-06 07:17:54"
    },
    {
      "urlChapter": "chapter-17",
      "dateUpdateChapter": "2023-12-06 07:17:51"
    },
    {
      "urlChapter": "chapter-16",
      "dateUpdateChapter": "2023-12-06 07:17:49"
    },
    {
      "urlChapter": "chapter-15",
      "dateUpdateChapter": "2023-12-06 07:17:46"
    },
    {
      "urlChapter": "chapter-14",
      "dateUpdateChapter": "2023-12-06 07:17:44"
    },
    {
      "urlChapter": "chapter-13",
      "dateUpdateChapter": "2023-12-06 07:17:41"
    },
    {
      "urlChapter": "chapter-12",
      "dateUpdateChapter": "2023-12-06 07:17:39"
    },
    {
      "urlChapter": "chapter-11",
      "dateUpdateChapter": "2023-12-06 07:17:36"
    },
    {
      "urlChapter": "chapter-10",
      "dateUpdateChapter": "2023-12-06 07:17:34"
    },
    {
      "urlChapter": "chapter-9",
      "dateUpdateChapter": "2023-12-06 07:17:32"
    },
    {
      "urlChapter": "chapter-8",
      "dateUpdateChapter": "2023-12-06 07:17:30"
    },
    {
      "urlChapter": "chapter-7",
      "dateUpdateChapter": "2023-12-06 07:17:28"
    },
    {
      "urlChapter": "chapter-6",
      "dateUpdateChapter": "2023-12-06 07:17:26"
    },
    {
      "urlChapter": "chapter-5",
      "dateUpdateChapter": "2023-12-06 07:17:24"
    },
    {
      "urlChapter": "chapter-4",
      "dateUpdateChapter": "2023-12-06 07:17:22"
    },
    {
      "urlChapter": "chapter-3",
      "dateUpdateChapter": "2023-12-06 07:17:20"
    },
    {
      "urlChapter": "chapter-2",
      "dateUpdateChapter": "2023-12-06 07:17:17"
    },
    {
      "urlChapter": "chapter-1",
      "dateUpdateChapter": "2023-12-06 07:17:14"
    }
  ]
}