{
  "Title": "Thanh \u0111\u1eb1ng chi luy\u1ebfn: Thi\u1ebfu gia tai ti\u1ebfng v\u00e0 n\u1eef h\u00e0i",
  "URL": "thanh-dang-chi-luyen-thieu-gia-tai-tieng-va-nu-hai",
  "CoverImage": "thanh-dang-chi-luyen-thieu-gia-tai-tieng-va-nu-hai.jpg",
  "CreateAt": "12/01/2024",
  "statusComic": 0,
  "Category": [
    "Comedy",
    "Manhua",
    "Ng\u00f4n T\u00ecnh",
    "Romance",
    "Shoujo",
    "Shounen",
    "Truy\u1ec7n M\u00e0u"
  ],
  "LastChapter": "chapter-33",
  "TotalChapter": 33,
  "Chapters": {
    "urlChapter": "chapter-33",
    "dateUpdateChapter": "2024-01-12 01:48:34"
  }
}