{
  "Title": "Thi\u1ebfu N\u1eef Ph\u00e1 Ho\u1ea1i v\u00e0 Ma Th\u1ea7n T\u00e2n N\u01b0\u01a1ng",
  "URL": "thieu-nu-pha-hoai-va-ma-than-tan-nuong",
  "CoverImage": "thieu-nu-pha-hoai-va-ma-than-tan-nuong.jpg",
  "CreateAt": "26/01/2024",
  "statusComic": 0,
  "Category": [
    "Fantasy",
    "Harem",
    "Manhua",
    "Supernatural",
    "Truy\u1ec7n M\u00e0u"
  ],
  "LastChapter": "chapter-15",
  "TotalChapter": 15,
  "Chapters": {
    "urlChapter": "chapter-15",
    "dateUpdateChapter": "2024-01-26 17:44:49"
  }
}