{
  "Title": "Thi\u00ean H\u00e0ng H\u1ec7 Ph\u00e1ch \u0110\u01b0\u01a1ng",
  "URL": "thien-hang-he-phach-duong",
  "CoverImage": "thien-hang-he-phach-duong.jpg",
  "CreateAt": "20/01/2024",
  "statusComic": 0,
  "Category": [
    "Action",
    "Comedy",
    "Drama",
    "Fantasy",
    "Manhua",
    "Romance",
    "Shounen",
    "Truy\u1ec7n M\u00e0u"
  ],
  "LastChapter": "chapter-21",
  "TotalChapter": 21,
  "Chapters": {
    "urlChapter": "chapter-21",
    "dateUpdateChapter": "2024-01-20 01:57:31"
  }
}