{
  "Title": "T\u00f4i L\u00e0 B\u1ea1n G\u00e1i C\u0169 C\u1ee7a M\u1ed9t Ng\u01b0\u1eddi L\u00ednh",
  "URL": "toi-la-ban-gai-cu-cua-mot-nguoi-linh",
  "CoverImage": "toi-la-ban-gai-cu-cua-mot-nguoi-linh.jpg",
  "CreateAt": "29/12/2023",
  "statusComic": 0,
  "Category": [
    "Chuy\u1ec3n Sinh",
    "Comedy",
    "Historical",
    "Manhwa",
    "Romance",
    "Truy\u1ec7n M\u00e0u"
  ],
  "LastChapter": "chapter-58",
  "TotalChapter": 58,
  "Chapters": {
    "urlChapter": "chapter-58",
    "dateUpdateChapter": "2023-12-29 23:17:32"
  }
}